{"authority":"advisory","edges":[{"attrs":{},"from":"n:module","id":"e:calls:Array.from:6502","kind":"Calls","symbol":"cp:Calls","to":"n:typeref:Array.from"},{"attrs":{},"from":"n:module","id":"e:calls:Date.now:3673","kind":"Calls","symbol":"cp:Calls","to":"n:typeref:Date.now"},{"attrs":{},"from":"n:module","id":"e:calls:Date.now:5727","kind":"Calls","symbol":"cp:Calls","to":"n:typeref:Date.now"},{"attrs":{},"from":"n:module","id":"e:calls:Date.now:5807","kind":"Calls","symbol":"cp:Calls","to":"n:typeref:Date.now"},{"attrs":{},"from":"n:module","id":"e:calls:Map:800","kind":"Calls","symbol":"cp:Calls","to":"n:typeref:Map"},{"attrs":{},"from":"n:module","id":"e:calls:Math.max:8288","kind":"Calls","symbol":"cp:Calls","to":"n:typeref:Math.max"},{"attrs":{},"from":"n:module","id":"e:calls:MemoryOptimizedAutomaton:2594","kind":"Calls","symbol":"cp:Calls","to":"n:typeref:MemoryOptimizedAutomaton"},{"attrs":{},"from":"n:module","id":"e:calls:automaton.destroy:3441","kind":"Calls","symbol":"cp:Calls","to":"n:typeref:automaton.destroy"},{"attrs":{},"from":"n:module","id":"e:calls:automaton.executeSelfModification:2849","kind":"Calls","symbol":"cp:Calls","to":"n:typeref:automaton.executeSelfModification"},{"attrs":{},"from":"n:module","id":"e:calls:automaton:2013","kind":"Calls","symbol":"cp:Calls","to":"n:typeref:automaton"},{"attrs":{},"from":"n:module","id":"e:calls:avgMem.toFixed:8391","kind":"Calls","symbol":"cp:Calls","to":"n:typeref:avgMem.toFixed"},{"attrs":{},"from":"n:module","id":"e:calls:child.kill:7995","kind":"Calls","symbol":"cp:Calls","to":"n:typeref:child.kill"},{"attrs":{},"from":"n:module","id":"e:calls:child.on:5028","kind":"Calls","symbol":"cp:Calls","to":"n:typeref:child.on"},{"attrs":{},"from":"n:module","id":"e:calls:child.on:5174","kind":"Calls","symbol":"cp:Calls","to":"n:typeref:child.on"},{"attrs":{},"from":"n:module","id":"e:calls:clearInterval:7817","kind":"Calls","symbol":"cp:Calls","to":"n:typeref:clearInterval"},{"attrs":{},"from":"n:module","id":"e:calls:console.error:2910","kind":"Calls","symbol":"cp:Calls","to":"n:typeref:console.error"},{"attrs":{},"from":"n:module","id":"e:calls:console.error:4955","kind":"Calls","symbol":"cp:Calls","to":"n:typeref:console.error"},{"attrs":{},"from":"n:module","id":"e:calls:console.error:5209","kind":"Calls","symbol":"cp:Calls","to":"n:typeref:console.error"},{"attrs":{},"from":"n:module","id":"e:calls:console.log:1978","kind":"Calls","symbol":"cp:Calls","to":"n:typeref:console.log"},{"attrs":{},"from":"n:module","id":"e:calls:console.log:3251","kind":"Calls","symbol":"cp:Calls","to":"n:typeref:console.log"},{"attrs":{},"from":"n:module","id":"e:calls:console.log:3486","kind":"Calls","symbol":"cp:Calls","to":"n:typeref:console.log"},{"attrs":{},"from":"n:module","id":"e:calls:console.log:4265","kind":"Calls","symbol":"cp:Calls","to":"n:typeref:console.log"},{"attrs":{},"from":"n:module","id":"e:calls:console.log:4360","kind":"Calls","symbol":"cp:Calls","to":"n:typeref:console.log"},{"attrs":{},"from":"n:module","id":"e:calls:console.log:4403","kind":"Calls","symbol":"cp:Calls","to":"n:typeref:console.log"},{"attrs":{},"from":"n:module","id":"e:calls:console.log:4847","kind":"Calls","symbol":"cp:Calls","to":"n:typeref:console.log"},{"attrs":{},"from":"n:module","id":"e:calls:console.log:5061","kind":"Calls","symbol":"cp:Calls","to":"n:typeref:console.log"},{"attrs":{},"from":"n:module","id":"e:calls:console.log:5825","kind":"Calls","symbol":"cp:Calls","to":"n:typeref:console.log"},{"attrs":{},"from":"n:module","id":"e:calls:console.log:6274","kind":"Calls","symbol":"cp:Calls","to":"n:typeref:console.log"},{"attrs":{},"from":"n:module","id":"e:calls:console.log:6439","kind":"Calls","symbol":"cp:Calls","to":"n:typeref:console.log"},{"attrs":{},"from":"n:module","id":"e:calls:console.log:6931","kind":"Calls","symbol":"cp:Calls","to":"n:typeref:console.log"},{"attrs":{},"from":"n:module","id":"e:calls:console.log:7081","kind":"Calls","symbol":"cp:Calls","to":"n:typeref:console.log"},{"attrs":{},"from":"n:module","id":"e:calls:console.log:7141","kind":"Calls","symbol":"cp:Calls","to":"n:typeref:console.log"},{"attrs":{},"from":"n:module","id":"e:calls:console.log:7205","kind":"Calls","symbol":"cp:Calls","to":"n:typeref:console.log"},{"attrs":{},"from":"n:module","id":"e:calls:console.log:7245","kind":"Calls","symbol":"cp:Calls","to":"n:typeref:console.log"},{"attrs":{},"from":"n:module","id":"e:calls:console.log:7316","kind":"Calls","symbol":"cp:Calls","to":"n:typeref:console.log"},{"attrs":{},"from":"n:module","id":"e:calls:console.log:7393","kind":"Calls","symbol":"cp:Calls","to":"n:typeref:console.log"},{"attrs":{},"from":"n:module","id":"e:calls:console.log:7466","kind":"Calls","symbol":"cp:Calls","to":"n:typeref:console.log"},{"attrs":{},"from":"n:module","id":"e:calls:console.log:7544","kind":"Calls","symbol":"cp:Calls","to":"n:typeref:console.log"},{"attrs":{},"from":"n:module","id":"e:calls:console.log:7764","kind":"Calls","symbol":"cp:Calls","to":"n:typeref:console.log"},{"attrs":{},"from":"n:module","id":"e:calls:console.log:7939","kind":"Calls","symbol":"cp:Calls","to":"n:typeref:console.log"},{"attrs":{},"from":"n:module","id":"e:calls:console.log:8026","kind":"Calls","symbol":"cp:Calls","to":"n:typeref:console.log"},{"attrs":{},"from":"n:module","id":"e:calls:console.log:8059","kind":"Calls","symbol":"cp:Calls","to":"n:typeref:console.log"},{"attrs":{},"from":"n:module","id":"e:calls:console.log:8357","kind":"Calls","symbol":"cp:Calls","to":"n:typeref:console.log"},{"attrs":{},"from":"n:module","id":"e:calls:console.log:8421","kind":"Calls","symbol":"cp:Calls","to":"n:typeref:console.log"},{"attrs":{},"from":"n:module","id":"e:calls:console.log:8486","kind":"Calls","symbol":"cp:Calls","to":"n:typeref:console.log"},{"attrs":{},"from":"n:module","id":"e:calls:console.log:8586","kind":"Calls","symbol":"cp:Calls","to":"n:typeref:console.log"},{"attrs":{},"from":"n:module","id":"e:calls:createOptimizedScript:1517","kind":"Calls","symbol":"cp:Calls","to":"n:typeref:createOptimizedScript"},{"attrs":{},"from":"n:module","id":"e:calls:createOptimizedScript:4215","kind":"Calls","symbol":"cp:Calls","to":"n:typeref:createOptimizedScript"},{"attrs":{},"from":"n:module","id":"e:calls:data.toString:4876","kind":"Calls","symbol":"cp:Calls","to":"n:typeref:data.toString"},{"attrs":{},"from":"n:module","id":"e:calls:data.toString:4990","kind":"Calls","symbol":"cp:Calls","to":"n:typeref:data.toString"},{"attrs":{},"from":"n:module","id":"e:calls:fs.writeFileSync:3540","kind":"Calls","symbol":"cp:Calls","to":"n:typeref:fs.writeFileSync"},{"attrs":{},"from":"n:module","id":"e:calls:getMemoryState:5358","kind":"Calls","symbol":"cp:Calls","to":"n:typeref:getMemoryState"},{"attrs":{},"from":"n:module","id":"e:calls:getMemoryState:936","kind":"Calls","symbol":"cp:Calls","to":"n:typeref:getMemoryState"},{"attrs":{},"from":"n:module","id":"e:calls:global.gc:5763","kind":"Calls","symbol":"cp:Calls","to":"n:typeref:global.gc"},{"attrs":{},"from":"n:module","id":"e:calls:join:6538","kind":"Calls","symbol":"cp:Calls","to":"n:typeref:join"},{"attrs":{},"from":"n:module","id":"e:calls:main:7070","kind":"Calls","symbol":"cp:Calls","to":"n:typeref:main"},{"attrs":{},"from":"n:module","id":"e:calls:main:8701","kind":"Calls","symbol":"cp:Calls","to":"n:typeref:main"},{"attrs":{},"from":"n:module","id":"e:calls:maxMem.toFixed:8452","kind":"Calls","symbol":"cp:Calls","to":"n:typeref:maxMem.toFixed"},{"attrs":{},"from":"n:module","id":"e:calls:memGrowth.toFixed:6984","kind":"Calls","symbol":"cp:Calls","to":"n:typeref:memGrowth.toFixed"},{"attrs":{},"from":"n:module","id":"e:calls:memMB.toFixed:3355","kind":"Calls","symbol":"cp:Calls","to":"n:typeref:memMB.toFixed"},{"attrs":{},"from":"n:module","id":"e:calls:memMB.toFixed:6299","kind":"Calls","symbol":"cp:Calls","to":"n:typeref:memMB.toFixed"},{"attrs":{},"from":"n:module","id":"e:calls:memoryHistory.map:8300","kind":"Calls","symbol":"cp:Calls","to":"n:typeref:memoryHistory.map"},{"attrs":{},"from":"n:module","id":"e:calls:memoryHistory.push:5378","kind":"Calls","symbol":"cp:Calls","to":"n:typeref:memoryHistory.push"},{"attrs":{},"from":"n:module","id":"e:calls:memoryHistory.reduce:8175","kind":"Calls","symbol":"cp:Calls","to":"n:typeref:memoryHistory.reduce"},{"attrs":{},"from":"n:module","id":"e:calls:memoryHistory.shift:5477","kind":"Calls","symbol":"cp:Calls","to":"n:typeref:memoryHistory.shift"},{"attrs":{},"from":"n:module","id":"e:calls:memoryHistory.slice:6659","kind":"Calls","symbol":"cp:Calls","to":"n:typeref:memoryHistory.slice"},{"attrs":{},"from":"n:module","id":"e:calls:monitorMemory:5318","kind":"Calls","symbol":"cp:Calls","to":"n:typeref:monitorMemory"},{"attrs":{},"from":"n:module","id":"e:calls:on:4820","kind":"Calls","symbol":"cp:Calls","to":"n:typeref:on"},{"attrs":{},"from":"n:module","id":"e:calls:on:4928","kind":"Calls","symbol":"cp:Calls","to":"n:typeref:on"},{"attrs":{},"from":"n:module","id":"e:calls:os.freemem:1055","kind":"Calls","symbol":"cp:Calls","to":"n:typeref:os.freemem"},{"attrs":{},"from":"n:module","id":"e:calls:os.totalmem:1034","kind":"Calls","symbol":"cp:Calls","to":"n:typeref:os.totalmem"},{"attrs":{},"from":"n:module","id":"e:calls:path.join:1608","kind":"Calls","symbol":"cp:Calls","to":"n:typeref:path.join"},{"attrs":{},"from":"n:module","id":"e:calls:pressure.toUpperCase:3268","kind":"Calls","symbol":"cp:Calls","to":"n:typeref:pressure.toUpperCase"},{"attrs":{},"from":"n:module","id":"e:calls:pressure.toUpperCase:4315","kind":"Calls","symbol":"cp:Calls","to":"n:typeref:pressure.toUpperCase"},{"attrs":{},"from":"n:module","id":"e:calls:process.exit:3464","kind":"Calls","symbol":"cp:Calls","to":"n:typeref:process.exit"},{"attrs":{},"from":"n:module","id":"e:calls:process.exit:8558","kind":"Calls","symbol":"cp:Calls","to":"n:typeref:process.exit"},{"attrs":{},"from":"n:module","id":"e:calls:process.memoryUsage:3048","kind":"Calls","symbol":"cp:Calls","to":"n:typeref:process.memoryUsage"},{"attrs":{},"from":"n:module","id":"e:calls:process.memoryUsage:982","kind":"Calls","symbol":"cp:Calls","to":"n:typeref:process.memoryUsage"},{"attrs":{},"from":"n:module","id":"e:calls:process.on:3410","kind":"Calls","symbol":"cp:Calls","to":"n:typeref:process.on"},{"attrs":{},"from":"n:module","id":"e:calls:process.on:7731","kind":"Calls","symbol":"cp:Calls","to":"n:typeref:process.on"},{"attrs":{},"from":"n:module","id":"e:calls:rssMB.toFixed:6328","kind":"Calls","symbol":"cp:Calls","to":"n:typeref:rssMB.toFixed"},{"attrs":{},"from":"n:module","id":"e:calls:setInterval:2817","kind":"Calls","symbol":"cp:Calls","to":"n:typeref:setInterval"},{"attrs":{},"from":"n:module","id":"e:calls:setInterval:3014","kind":"Calls","symbol":"cp:Calls","to":"n:typeref:setInterval"},{"attrs":{},"from":"n:module","id":"e:calls:setInterval:7645","kind":"Calls","symbol":"cp:Calls","to":"n:typeref:setInterval"},{"attrs":{},"from":"n:module","id":"e:calls:spawn:4468","kind":"Calls","symbol":"cp:Calls","to":"n:typeref:spawn"},{"attrs":{},"from":"n:module","id":"e:calls:spawnOptimizedVersion:3611","kind":"Calls","symbol":"cp:Calls","to":"n:typeref:spawnOptimizedVersion"},{"attrs":{},"from":"n:module","id":"e:calls:spawnOptimizedVersion:6008","kind":"Calls","symbol":"cp:Calls","to":"n:typeref:spawnOptimizedVersion"},{"attrs":{},"from":"n:module","id":"e:calls:spawnedProcesses.delete:5128","kind":"Calls","symbol":"cp:Calls","to":"n:typeref:spawnedProcesses.delete"},{"attrs":{},"from":"n:module","id":"e:calls:spawnedProcesses.delete:5265","kind":"Calls","symbol":"cp:Calls","to":"n:typeref:spawnedProcesses.delete"},{"attrs":{},"from":"n:module","id":"e:calls:spawnedProcesses.forEach:7885","kind":"Calls","symbol":"cp:Calls","to":"n:typeref:spawnedProcesses.forEach"},{"attrs":{},"from":"n:module","id":"e:calls:spawnedProcesses.get:3888","kind":"Calls","symbol":"cp:Calls","to":"n:typeref:spawnedProcesses.get"},{"attrs":{},"from":"n:module","id":"e:calls:spawnedProcesses.has:3833","kind":"Calls","symbol":"cp:Calls","to":"n:typeref:spawnedProcesses.has"},{"attrs":{},"from":"n:module","id":"e:calls:spawnedProcesses.keys:6513","kind":"Calls","symbol":"cp:Calls","to":"n:typeref:spawnedProcesses.keys"},{"attrs":{},"from":"n:module","id":"e:calls:spawnedProcesses.set:4723","kind":"Calls","symbol":"cp:Calls","to":"n:typeref:spawnedProcesses.set"},{"attrs":{},"from":"n:module","id":"e:calls:state.pressure.toUpperCase:6402","kind":"Calls","symbol":"cp:Calls","to":"n:typeref:state.pressure.toUpperCase"},{"attrs":{},"from":"n:module","id":"e:calls:systemFreeMB.toFixed:6356","kind":"Calls","symbol":"cp:Calls","to":"n:typeref:systemFreeMB.toFixed"},{"attrs":{},"from":"n:module","id":"e:calls:triggered:5843","kind":"Calls","symbol":"cp:Calls","to":"n:typeref:triggered"},{"attrs":{},"from":"n:module","id":"e:calls:trim:4892","kind":"Calls","symbol":"cp:Calls","to":"n:typeref:trim"},{"attrs":{},"from":"n:module","id":"e:calls:trim:5006","kind":"Calls","symbol":"cp:Calls","to":"n:typeref:trim"},{"attrs":{},"from":"n:module","id":"e:defines:function:createOptimizedScript","kind":"Defines","symbol":"cp:Defines","to":"n:function:createOptimizedScript"},{"attrs":{},"from":"n:module","id":"e:defines:function:getMemoryState","kind":"Defines","symbol":"cp:Defines","to":"n:function:getMemoryState"},{"attrs":{},"from":"n:module","id":"e:defines:function:main","kind":"Defines","symbol":"cp:Defines","to":"n:function:main"},{"attrs":{},"from":"n:module","id":"e:defines:function:monitorMemory","kind":"Defines","symbol":"cp:Defines","to":"n:function:monitorMemory"},{"attrs":{},"from":"n:module","id":"e:defines:function:spawnOptimizedVersion","kind":"Defines","symbol":"cp:Defines","to":"n:function:spawnOptimizedVersion"},{"attrs":{},"from":"n:module","id":"e:imports:./automaton-memory-optimized:1826","kind":"Imports","symbol":"cp:Imports","to":"n:import:./automaton-memory-optimized"},{"attrs":{},"from":"n:module","id":"e:imports:child_process:134","kind":"Imports","symbol":"cp:Imports","to":"n:import:child_process"},{"attrs":{},"from":"n:module","id":"e:imports:fs:188","kind":"Imports","symbol":"cp:Imports","to":"n:import:fs"},{"attrs":{},"from":"n:module","id":"e:imports:os:244","kind":"Imports","symbol":"cp:Imports","to":"n:import:os"},{"attrs":{},"from":"n:module","id":"e:imports:path:214","kind":"Imports","symbol":"cp:Imports","to":"n:import:path"}],"graph_hash":"sha256:842e5b8ca70dca9c54bad1ee63ec3add2119d5d0761ea69b5becad4d29d4f641","language":"typescript","namespace":"analysis.typescript.automaton-memory-spawner.ts","nodes":[{"attrs":{"name":"createOptimizedScript"},"id":"n:function:createOptimizedScript","kind":"Function","source":{"column":0,"end_column":31,"end_line":56,"line":55,"path":"automaton-memory-spawner.ts"},"symbol":"cp:Function"},{"attrs":{"name":"getMemoryState"},"id":"n:function:getMemoryState","kind":"Function","source":{"column":0,"end_column":24,"end_line":33,"line":32,"path":"automaton-memory-spawner.ts"},"symbol":"cp:Function"},{"attrs":{"name":"main"},"id":"n:function:main","kind":"Function","source":{"column":0,"end_column":14,"end_line":227,"line":226,"path":"automaton-memory-spawner.ts"},"symbol":"cp:Function"},{"attrs":{"name":"monitorMemory"},"id":"n:function:monitorMemory","kind":"Function","source":{"column":0,"end_column":23,"end_line":178,"line":177,"path":"automaton-memory-spawner.ts"},"symbol":"cp:Function"},{"attrs":{"name":"spawnOptimizedVersion"},"id":"n:function:spawnOptimizedVersion","kind":"Function","source":{"column":0,"end_column":31,"end_line":118,"line":117,"path":"automaton-memory-spawner.ts"},"symbol":"cp:Function"},{"attrs":{"name":"./automaton-memory-optimized"},"id":"n:import:./automaton-memory-optimized","kind":"Namespace","source":{"column":0,"end_column":72,"end_line":66,"line":65,"path":"automaton-memory-spawner.ts"},"symbol":"cp:Namespace"},{"attrs":{"name":"child_process"},"id":"n:import:child_process","kind":"Namespace","source":{"column":0,"end_column":52,"end_line":7,"line":6,"path":"automaton-memory-spawner.ts"},"symbol":"cp:Namespace"},{"attrs":{"name":"fs"},"id":"n:import:fs","kind":"Namespace","source":{"column":0,"end_column":25,"end_line":8,"line":8,"path":"automaton-memory-spawner.ts"},"symbol":"cp:Namespace"},{"attrs":{"name":"os"},"id":"n:import:os","kind":"Namespace","source":{"column":0,"end_column":25,"end_line":10,"line":10,"path":"automaton-memory-spawner.ts"},"symbol":"cp:Namespace"},{"attrs":{"name":"path"},"id":"n:import:path","kind":"Namespace","source":{"column":0,"end_column":29,"end_line":9,"line":9,"path":"automaton-memory-spawner.ts"},"symbol":"cp:Namespace"},{"attrs":{"name":"automaton-memory-spawner.ts"},"id":"n:module","kind":"Module","source":{"column":0,"end_column":64,"end_line":271,"line":1,"path":"automaton-memory-spawner.ts"},"symbol":"cp:Module"},{"attrs":{"name":"Array.from"},"id":"n:typeref:Array.from","kind":"TypeRef","source":{"column":67,"end_column":78,"end_line":210,"line":210,"path":"automaton-memory-spawner.ts"},"symbol":"cp:TypeRef"},{"attrs":{"name":"Date.now"},"id":"n:typeref:Date.now","kind":"TypeRef","source":{"column":14,"end_column":23,"end_line":119,"line":119,"path":"automaton-memory-spawner.ts"},"symbol":"cp:TypeRef"},{"attrs":{"name":"Map"},"id":"n:typeref:Map","kind":"TypeRef","source":{"column":54,"end_column":58,"end_line":28,"line":28,"path":"automaton-memory-spawner.ts"},"symbol":"cp:TypeRef"},{"attrs":{"name":"Math.max"},"id":"n:typeref:Math.max","kind":"TypeRef","source":{"column":21,"end_column":30,"end_line":255,"line":255,"path":"automaton-memory-spawner.ts"},"symbol":"cp:TypeRef"},{"attrs":{"name":"MemoryOptimizedAutomaton"},"id":"n:typeref:MemoryOptimizedAutomaton","kind":"TypeRef","source":{"column":22,"end_column":47,"end_line":83,"line":83,"path":"automaton-memory-spawner.ts"},"symbol":"cp:TypeRef"},{"attrs":{"name":"automaton"},"id":"n:typeref:automaton","kind":"TypeRef","source":{"column":35,"end_column":46,"end_line":71,"line":71,"path":"automaton-memory-spawner.ts"},"symbol":"cp:TypeRef"},{"attrs":{"name":"automaton.destroy"},"id":"n:typeref:automaton.destroy","kind":"TypeRef","source":{"column":2,"end_column":20,"end_line":107,"line":107,"path":"automaton-memory-spawner.ts"},"symbol":"cp:TypeRef"},{"attrs":{"name":"automaton.executeSelfModification"},"id":"n:typeref:automaton.executeSelfModification","kind":"TypeRef","source":{"column":4,"end_column":38,"end_line":90,"line":90,"path":"automaton-memory-spawner.ts"},"symbol":"cp:TypeRef"},{"attrs":{"name":"avgMem.toFixed"},"id":"n:typeref:avgMem.toFixed","kind":"TypeRef","source":{"column":40,"end_column":55,"end_line":256,"line":256,"path":"automaton-memory-spawner.ts"},"symbol":"cp:TypeRef"},{"attrs":{"name":"child.kill"},"id":"n:typeref:child.kill","kind":"TypeRef","source":{"column":6,"end_column":17,"end_line":248,"line":248,"path":"automaton-memory-spawner.ts"},"symbol":"cp:TypeRef"},{"attrs":{"name":"child.on"},"id":"n:typeref:child.on","kind":"TypeRef","source":{"column":2,"end_column":11,"end_line":167,"line":167,"path":"automaton-memory-spawner.ts"},"symbol":"cp:TypeRef"},{"attrs":{"name":"clearInterval"},"id":"n:typeref:clearInterval","kind":"TypeRef","source":{"column":4,"end_column":18,"end_line":243,"line":243,"path":"automaton-memory-spawner.ts"},"symbol":"cp:TypeRef"},{"attrs":{"name":"console.error"},"id":"n:typeref:console.error","kind":"TypeRef","source":{"column":4,"end_column":18,"end_line":92,"line":92,"path":"automaton-memory-spawner.ts"},"symbol":"cp:TypeRef"},{"attrs":{"name":"console.log"},"id":"n:typeref:console.log","kind":"TypeRef","source":{"column":0,"end_column":12,"end_line":71,"line":71,"path":"automaton-memory-spawner.ts"},"symbol":"cp:TypeRef"},{"attrs":{"name":"createOptimizedScript"},"id":"n:typeref:createOptimizedScript","kind":"TypeRef","source":{"column":9,"end_column":31,"end_line":56,"line":56,"path":"automaton-memory-spawner.ts"},"symbol":"cp:TypeRef"},{"attrs":{"name":"data.toString"},"id":"n:typeref:data.toString","kind":"TypeRef","source":{"column":33,"end_column":47,"end_line":160,"line":160,"path":"automaton-memory-spawner.ts"},"symbol":"cp:TypeRef"},{"attrs":{"name":"fs.writeFileSync"},"id":"n:typeref:fs.writeFileSync","kind":"TypeRef","source":{"column":2,"end_column":19,"end_line":114,"line":114,"path":"automaton-memory-spawner.ts"},"symbol":"cp:TypeRef"},{"attrs":{"name":"getMemoryState"},"id":"n:typeref:getMemoryState","kind":"TypeRef","source":{"column":9,"end_column":24,"end_line":33,"line":33,"path":"automaton-memory-spawner.ts"},"symbol":"cp:TypeRef"},{"attrs":{"name":"global.gc"},"id":"n:typeref:global.gc","kind":"TypeRef","source":{"column":6,"end_column":16,"end_line":192,"line":192,"path":"automaton-memory-spawner.ts"},"symbol":"cp:TypeRef"},{"attrs":{"name":"join"},"id":"n:typeref:join","kind":"TypeRef","source":{"column":103,"end_column":108,"end_line":210,"line":210,"path":"automaton-memory-spawner.ts"},"symbol":"cp:TypeRef"},{"attrs":{"name":"main"},"id":"n:typeref:main","kind":"TypeRef","source":{"column":9,"end_column":14,"end_line":227,"line":227,"path":"automaton-memory-spawner.ts"},"symbol":"cp:TypeRef"},{"attrs":{"name":"maxMem.toFixed"},"id":"n:typeref:maxMem.toFixed","kind":"TypeRef","source":{"column":37,"end_column":52,"end_line":257,"line":257,"path":"automaton-memory-spawner.ts"},"symbol":"cp:TypeRef"},{"attrs":{"name":"memGrowth.toFixed"},"id":"n:typeref:memGrowth.toFixed","kind":"TypeRef","source":{"column":63,"end_column":81,"end_line":220,"line":220,"path":"automaton-memory-spawner.ts"},"symbol":"cp:TypeRef"},{"attrs":{"name":"memMB.toFixed"},"id":"n:typeref:memMB.toFixed","kind":"TypeRef","source":{"column":106,"end_column":120,"end_line":102,"line":102,"path":"automaton-memory-spawner.ts"},"symbol":"cp:TypeRef"},{"attrs":{"name":"memoryHistory.map"},"id":"n:typeref:memoryHistory.map","kind":"TypeRef","source":{"column":33,"end_column":51,"end_line":255,"line":255,"path":"automaton-memory-spawner.ts"},"symbol":"cp:TypeRef"},{"attrs":{"name":"memoryHistory.push"},"id":"n:typeref:memoryHistory.push","kind":"TypeRef","source":{"column":2,"end_column":21,"end_line":180,"line":180,"path":"automaton-memory-spawner.ts"},"symbol":"cp:TypeRef"},{"attrs":{"name":"memoryHistory.reduce"},"id":"n:typeref:memoryHistory.reduce","kind":"TypeRef","source":{"column":21,"end_column":42,"end_line":254,"line":254,"path":"automaton-memory-spawner.ts"},"symbol":"cp:TypeRef"},{"attrs":{"name":"memoryHistory.shift"},"id":"n:typeref:memoryHistory.shift","kind":"TypeRef","source":{"column":4,"end_column":24,"end_line":184,"line":184,"path":"automaton-memory-spawner.ts"},"symbol":"cp:TypeRef"},{"attrs":{"name":"memoryHistory.slice"},"id":"n:typeref:memoryHistory.slice","kind":"TypeRef","source":{"column":21,"end_column":41,"end_line":214,"line":214,"path":"automaton-memory-spawner.ts"},"symbol":"cp:TypeRef"},{"attrs":{"name":"monitorMemory"},"id":"n:typeref:monitorMemory","kind":"TypeRef","source":{"column":9,"end_column":23,"end_line":178,"line":178,"path":"automaton-memory-spawner.ts"},"symbol":"cp:TypeRef"},{"attrs":{"name":"on"},"id":"n:typeref:on","kind":"TypeRef","source":{"column":16,"end_column":19,"end_line":159,"line":159,"path":"automaton-memory-spawner.ts"},"symbol":"cp:TypeRef"},{"attrs":{"name":"os.freemem"},"id":"n:typeref:os.freemem","kind":"TypeRef","source":{"column":50,"end_column":61,"end_line":35,"line":35,"path":"automaton-memory-spawner.ts"},"symbol":"cp:TypeRef"},{"attrs":{"name":"os.totalmem"},"id":"n:typeref:os.totalmem","kind":"TypeRef","source":{"column":29,"end_column":41,"end_line":35,"line":35,"path":"automaton-memory-spawner.ts"},"symbol":"cp:TypeRef"},{"attrs":{"name":"path.join"},"id":"n:typeref:path.join","kind":"TypeRef","source":{"column":21,"end_column":31,"end_line":57,"line":57,"path":"automaton-memory-spawner.ts"},"symbol":"cp:TypeRef"},{"attrs":{"name":"pressure.toUpperCase"},"id":"n:typeref:pressure.toUpperCase","kind":"TypeRef","source":{"column":19,"end_column":40,"end_line":102,"line":102,"path":"automaton-memory-spawner.ts"},"symbol":"cp:TypeRef"},{"attrs":{"name":"process.exit"},"id":"n:typeref:process.exit","kind":"TypeRef","source":{"column":2,"end_column":15,"end_line":108,"line":108,"path":"automaton-memory-spawner.ts"},"symbol":"cp:TypeRef"},{"attrs":{"name":"process.memoryUsage"},"id":"n:typeref:process.memoryUsage","kind":"TypeRef","source":{"column":14,"end_column":34,"end_line":34,"line":34,"path":"automaton-memory-spawner.ts"},"symbol":"cp:TypeRef"},{"attrs":{"name":"process.on"},"id":"n:typeref:process.on","kind":"TypeRef","source":{"column":0,"end_column":11,"end_line":106,"line":106,"path":"automaton-memory-spawner.ts"},"symbol":"cp:TypeRef"},{"attrs":{"name":"rssMB.toFixed"},"id":"n:typeref:rssMB.toFixed","kind":"TypeRef","source":{"column":58,"end_column":72,"end_line":209,"line":209,"path":"automaton-memory-spawner.ts"},"symbol":"cp:TypeRef"},{"attrs":{"name":"setInterval"},"id":"n:typeref:setInterval","kind":"TypeRef","source":{"column":0,"end_column":12,"end_line":88,"line":88,"path":"automaton-memory-spawner.ts"},"symbol":"cp:TypeRef"},{"attrs":{"name":"spawn"},"id":"n:typeref:spawn","kind":"TypeRef","source":{"column":16,"end_column":22,"end_line":145,"line":145,"path":"automaton-memory-spawner.ts"},"symbol":"cp:TypeRef"},{"attrs":{"name":"spawnOptimizedVersion"},"id":"n:typeref:spawnOptimizedVersion","kind":"TypeRef","source":{"column":9,"end_column":31,"end_line":118,"line":118,"path":"automaton-memory-spawner.ts"},"symbol":"cp:TypeRef"},{"attrs":{"name":"spawnedProcesses.delete"},"id":"n:typeref:spawnedProcesses.delete","kind":"TypeRef","source":{"column":4,"end_column":28,"end_line":169,"line":169,"path":"automaton-memory-spawner.ts"},"symbol":"cp:TypeRef"},{"attrs":{"name":"spawnedProcesses.forEach"},"id":"n:typeref:spawnedProcesses.forEach","kind":"TypeRef","source":{"column":4,"end_column":29,"end_line":246,"line":246,"path":"automaton-memory-spawner.ts"},"symbol":"cp:TypeRef"},{"attrs":{"name":"spawnedProcesses.get"},"id":"n:typeref:spawnedProcesses.get","kind":"TypeRef","source":{"column":21,"end_column":42,"end_line":128,"line":128,"path":"automaton-memory-spawner.ts"},"symbol":"cp:TypeRef"},{"attrs":{"name":"spawnedProcesses.has"},"id":"n:typeref:spawnedProcesses.has","kind":"TypeRef","source":{"column":6,"end_column":27,"end_line":127,"line":127,"path":"automaton-memory-spawner.ts"},"symbol":"cp:TypeRef"},{"attrs":{"name":"spawnedProcesses.keys"},"id":"n:typeref:spawnedProcesses.keys","kind":"TypeRef","source":{"column":78,"end_column":100,"end_line":210,"line":210,"path":"automaton-memory-spawner.ts"},"symbol":"cp:TypeRef"},{"attrs":{"name":"spawnedProcesses.set"},"id":"n:typeref:spawnedProcesses.set","kind":"TypeRef","source":{"column":2,"end_column":23,"end_line":155,"line":155,"path":"automaton-memory-spawner.ts"},"symbol":"cp:TypeRef"},{"attrs":{"name":"state.pressure.toUpperCase"},"id":"n:typeref:state.pressure.toUpperCase","kind":"TypeRef","source":{"column":132,"end_column":159,"end_line":209,"line":209,"path":"automaton-memory-spawner.ts"},"symbol":"cp:TypeRef"},{"attrs":{"name":"systemFreeMB.toFixed"},"id":"n:typeref:systemFreeMB.toFixed","kind":"TypeRef","source":{"column":86,"end_column":107,"end_line":209,"line":209,"path":"automaton-memory-spawner.ts"},"symbol":"cp:TypeRef"},{"attrs":{"name":"triggered"},"id":"n:typeref:triggered","kind":"TypeRef","source":{"column":24,"end_column":35,"end_line":194,"line":194,"path":"automaton-memory-spawner.ts"},"symbol":"cp:TypeRef"},{"attrs":{"name":"trim"},"id":"n:typeref:trim","kind":"TypeRef","source":{"column":49,"end_column":54,"end_line":160,"line":160,"path":"automaton-memory-spawner.ts"},"symbol":"cp:TypeRef"}],"provenance":{"parser":"typescript-regex","parser_version":"v0","source_path":"automaton-memory-spawner.ts"},"v":"ak.asg.v0"}
