{"authority":"advisory","evidence_digest":"sha256:192459cf9ecd6fcb3480a43684e862ead3d825fc9d014f7b19b0ded0bdc54514","inputs_digest":"sha256:5be9c99840ef90a9cc4c7a649263bcceb290c8e77b027a8ea776a82b0be124a5","instances":[{"confidence":0.86,"evidence_edges":["e:imports:./canbc.js:46","e:imports:./canisa.js:169"],"file":"archive/tetragrammatron-os/tools/canbc/cli.mjs","language":"mjs","pattern_id":"pi.boundary_split.archive.tetragrammatron-os.tools.canbc.cli.mjs","pattern_type":"BoundarySplit","source_frame_hash":"163ce36409deed8f03a2bef8257f45dd81a18c19b42eaf7dec97c7ca4add4141","subject_nodes":["n:module"]},{"confidence":0.86,"evidence_edges":["e:imports:../tools/canbc/canbc.js:223","e:imports:../tools/canbc/canisa.js:152"],"file":"scripts/bench-can-vm.mjs","language":"mjs","pattern_id":"pi.boundary_split.scripts.bench-can-vm.mjs","pattern_type":"BoundarySplit","source_frame_hash":"f5151fec6f91c822ed3be3818e5f3a7a288e7fd0db73dee4a222512ce406b882","subject_nodes":["n:module"]},{"confidence":0.86,"evidence_edges":["e:imports:../tools/canbc/canbc.js:223","e:imports:../tools/canbc/canisa.js:152"],"file":"scripts/run-can-vm-vectors.mjs","language":"mjs","pattern_id":"pi.boundary_split.scripts.run-can-vm-vectors.mjs","pattern_type":"BoundarySplit","source_frame_hash":"0fdd87f0366b150416c01a123b9b09457fface81bea4c43936bc09aa404d8a3e","subject_nodes":["n:module"]},{"confidence":0.86,"evidence_edges":["e:imports:./canbc.js:46","e:imports:./canisa.js:169"],"file":"tools/canbc/cli.mjs","language":"mjs","pattern_id":"pi.boundary_split.tools.canbc.cli.mjs","pattern_type":"BoundarySplit","source_frame_hash":"1f339a7e70856b9cce50a7a871fb84169b4b08e5e3af7e3d3cde05c463df9b8c","subject_nodes":["n:module"]},{"confidence":0.82,"evidence_edges":["e:calls:readCanbc:2265","e:calls:runCanbc:3033","e:calls:assembleCanisa:1219","e:imports:./canisa.js:169"],"file":"archive/tetragrammatron-os/tools/canbc/cli.mjs","language":"mjs","pattern_id":"pi.bridge_layer.archive.tetragrammatron-os.tools.canbc.cli.mjs","pattern_type":"BridgeLayer","source_frame_hash":"163ce36409deed8f03a2bef8257f45dd81a18c19b42eaf7dec97c7ca4add4141","subject_nodes":["n:module"]},{"confidence":0.82,"evidence_edges":["e:calls:runCanbc:2621","e:calls:runCanbc:3327","e:calls:assembleCanisa:1963","e:calls:assembleCanisa:2219"],"file":"scripts/bench-can-vm.mjs","language":"mjs","pattern_id":"pi.bridge_layer.scripts.bench-can-vm.mjs","pattern_type":"BridgeLayer","source_frame_hash":"f5151fec6f91c822ed3be3818e5f3a7a288e7fd0db73dee4a222512ce406b882","subject_nodes":["n:module"]},{"confidence":0.82,"evidence_edges":["e:calls:runCanbc:1604","e:calls:writeCanbc:1287","e:calls:assembleCanisa:1201"],"file":"scripts/run-can-vm-vectors.mjs","language":"mjs","pattern_id":"pi.bridge_layer.scripts.run-can-vm-vectors.mjs","pattern_type":"BridgeLayer","source_frame_hash":"0fdd87f0366b150416c01a123b9b09457fface81bea4c43936bc09aa404d8a3e","subject_nodes":["n:module"]},{"confidence":0.82,"evidence_edges":["e:calls:readCanbc:2265","e:calls:runCanbc:3033","e:calls:assembleCanisa:1219","e:imports:./canisa.js:169"],"file":"tools/canbc/cli.mjs","language":"mjs","pattern_id":"pi.bridge_layer.tools.canbc.cli.mjs","pattern_type":"BridgeLayer","source_frame_hash":"1f339a7e70856b9cce50a7a871fb84169b4b08e5e3af7e3d3cde05c463df9b8c","subject_nodes":["n:module"]},{"confidence":0.8,"evidence_edges":["e:calls:JSON.parse:1845"],"file":"archive/tetragrammatron-os/tests/unit/test_hw_canon.mjs","language":"mjs","pattern_id":"pi.carrier_layer.archive.tetragrammatron-os.tests.unit.test_hw_canon.mjs","pattern_type":"CarrierLayer","source_frame_hash":"646aefb8e278bbda1c772281e4a03b2e330cb1ef7df8c020a5710aa97dab48a4","subject_nodes":["n:module"]},{"confidence":0.8,"evidence_edges":["e:calls:JSON.parse:2186"],"file":"archive/tetragrammatron-os/tests/unit/test_hw_project.mjs","language":"mjs","pattern_id":"pi.carrier_layer.archive.tetragrammatron-os.tests.unit.test_hw_project.mjs","pattern_type":"CarrierLayer","source_frame_hash":"e204501b223d32e7956ac3e576e139586947f93796856849487088f53b5763f5","subject_nodes":["n:module"]},{"confidence":0.8,"evidence_edges":["e:calls:console.error:1104"],"file":"archive/tetragrammatron-os/tests/unit/test_validate_jsonl.mjs","language":"mjs","pattern_id":"pi.carrier_layer.archive.tetragrammatron-os.tests.unit.test_validate_jsonl.mjs","pattern_type":"CarrierLayer","source_frame_hash":"2e34af2413867bfc7c3a9730524a4be06a16966e2050f40fb9cac72e42b0dd7d","subject_nodes":["n:module"]},{"confidence":0.8,"evidence_edges":["e:calls:HASH_EXTS.has:2118"],"file":"archive/tetragrammatron-os/tools/drift_scan.mjs","language":"mjs","pattern_id":"pi.carrier_layer.archive.tetragrammatron-os.tools.drift_scan.mjs","pattern_type":"CarrierLayer","source_frame_hash":"da47fade171fb3979196537ec5903778903b2fcf0577f01b9a2b7c8657dc0999","subject_nodes":["n:module"]},{"confidence":0.8,"evidence_edges":["e:calls:JSON.parse:1058"],"file":"archive/tetragrammatron-os/tools/hw_canon.mjs","language":"mjs","pattern_id":"pi.carrier_layer.archive.tetragrammatron-os.tools.hw_canon.mjs","pattern_type":"CarrierLayer","source_frame_hash":"2531db0fe856aebcbd5bbe74e5ca3ee23c6c44889e869a7281f30e3c3d1f71f9","subject_nodes":["n:module"]},{"confidence":0.8,"evidence_edges":["e:calls:JSON.parse:311"],"file":"archive/tetragrammatron-os/tools/hw_project.mjs","language":"mjs","pattern_id":"pi.carrier_layer.archive.tetragrammatron-os.tools.hw_project.mjs","pattern_type":"CarrierLayer","source_frame_hash":"8bc64be7793a9466019f2005b97162f7c3c56343f8cc481c28cde504e10a35ce","subject_nodes":["n:module"]},{"confidence":0.8,"evidence_edges":["e:calls:Array.isArray:1084"],"file":"archive/tetragrammatron-os/tools/validate_jsonl.mjs","language":"mjs","pattern_id":"pi.carrier_layer.archive.tetragrammatron-os.tools.validate_jsonl.mjs","pattern_type":"CarrierLayer","source_frame_hash":"78dba5125299661e5b35efc08a963c124b22867314037f1d350ae32828366cb1","subject_nodes":["n:module"]},{"confidence":0.8,"evidence_edges":["e:calls:JSON.parse:1845"],"file":"tests/unit/test_hw_canon.mjs","language":"mjs","pattern_id":"pi.carrier_layer.tests.unit.test_hw_canon.mjs","pattern_type":"CarrierLayer","source_frame_hash":"3214f98484fde0f4dcd25e3b77630fd7f248271faa5e3a93d54c651c8b58d0a4","subject_nodes":["n:module"]},{"confidence":0.8,"evidence_edges":["e:calls:JSON.parse:2186"],"file":"tests/unit/test_hw_project.mjs","language":"mjs","pattern_id":"pi.carrier_layer.tests.unit.test_hw_project.mjs","pattern_type":"CarrierLayer","source_frame_hash":"4e1145aae7c626a63e7e5d0eee3f102c2a68fb72c82e7df2feb5e40f0dd6de97","subject_nodes":["n:module"]},{"confidence":0.8,"evidence_edges":["e:calls:console.error:1104"],"file":"tests/unit/test_validate_jsonl.mjs","language":"mjs","pattern_id":"pi.carrier_layer.tests.unit.test_validate_jsonl.mjs","pattern_type":"CarrierLayer","source_frame_hash":"f78449d25bb9379a8ff628c013ea254d5b941d84fc2a1c0525a4d24f41a7dda3","subject_nodes":["n:module"]},{"confidence":0.8,"evidence_edges":["e:calls:HASH_EXTS.has:2118"],"file":"tools/drift_scan.mjs","language":"mjs","pattern_id":"pi.carrier_layer.tools.drift_scan.mjs","pattern_type":"CarrierLayer","source_frame_hash":"a3a4e56952a666d282d28ffbcf9188643b44d5bacd0612875771ca6761531e28","subject_nodes":["n:module"]},{"confidence":0.8,"evidence_edges":["e:calls:JSON.parse:1058"],"file":"tools/hw_canon.mjs","language":"mjs","pattern_id":"pi.carrier_layer.tools.hw_canon.mjs","pattern_type":"CarrierLayer","source_frame_hash":"9998ea10d104703b06a12840917f3065834617c2e3e2c21a0a4149668ca75a6b","subject_nodes":["n:module"]},{"confidence":0.8,"evidence_edges":["e:calls:JSON.parse:311"],"file":"tools/hw_project.mjs","language":"mjs","pattern_id":"pi.carrier_layer.tools.hw_project.mjs","pattern_type":"CarrierLayer","source_frame_hash":"1d6687d928258deeddf10c4c42ceedd301de0260fb80a97a934a2c3a1eb284ee","subject_nodes":["n:module"]},{"confidence":0.8,"evidence_edges":["e:calls:Array.isArray:1084"],"file":"tools/validate_jsonl.mjs","language":"mjs","pattern_id":"pi.carrier_layer.tools.validate_jsonl.mjs","pattern_type":"CarrierLayer","source_frame_hash":"10a37a3b0527514c679e8599b160647ad2a54051dea0b06a8ce74c04be30d9c7","subject_nodes":["n:module"]},{"confidence":0.82,"evidence_edges":["e:calls:test:1267","e:calls:test:3014","e:calls:JSON.parse:2407"],"file":"archive/tetragrammatron-os/tests/integration/test_pipeline.mjs","language":"mjs","pattern_id":"pi.conformance_surface.archive.tetragrammatron-os.tests.integration.test_pipeline.mjs","pattern_type":"ConformanceSurface","source_frame_hash":"1da5b5414ab50e4ae4e1ba29b5e947d3670f5d1ba7dafda4fee298562177aca6","subject_nodes":["n:module"]},{"confidence":0.82,"evidence_edges":["e:calls:runTest:918","e:calls:console.error:1152"],"file":"archive/tetragrammatron-os/tests/run_all.mjs","language":"mjs","pattern_id":"pi.conformance_surface.archive.tetragrammatron-os.tests.run_all.mjs","pattern_type":"ConformanceSurface","source_frame_hash":"46ffe9bec08495fe0601499ab4a84920f1d305977b74feea3aa27f91e0b0bb75","subject_nodes":["n:module"]},{"confidence":0.82,"evidence_edges":["e:calls:test:1212","e:calls:test:3943","e:calls:Array.isArray:2361"],"file":"archive/tetragrammatron-os/tests/unit/test_gen_indexes.mjs","language":"mjs","pattern_id":"pi.conformance_surface.archive.tetragrammatron-os.tests.unit.test_gen_indexes.mjs","pattern_type":"ConformanceSurface","source_frame_hash":"f6f9b250dcc08ac2078e48c8474dbce71b6a2461a7c375657411a814187fec52","subject_nodes":["n:module"]},{"confidence":0.82,"evidence_edges":["e:calls:test:1195","e:calls:test:2322","e:calls:JSON.parse:1845"],"file":"archive/tetragrammatron-os/tests/unit/test_hw_canon.mjs","language":"mjs","pattern_id":"pi.conformance_surface.archive.tetragrammatron-os.tests.unit.test_hw_canon.mjs","pattern_type":"ConformanceSurface","source_frame_hash":"646aefb8e278bbda1c772281e4a03b2e330cb1ef7df8c020a5710aa97dab48a4","subject_nodes":["n:module"]},{"confidence":0.82,"evidence_edges":["e:calls:test:1204","e:calls:test:2884","e:calls:JSON.parse:2186"],"file":"archive/tetragrammatron-os/tests/unit/test_hw_project.mjs","language":"mjs","pattern_id":"pi.conformance_surface.archive.tetragrammatron-os.tests.unit.test_hw_project.mjs","pattern_type":"ConformanceSurface","source_frame_hash":"e204501b223d32e7956ac3e576e139586947f93796856849487088f53b5763f5","subject_nodes":["n:module"]},{"confidence":0.82,"evidence_edges":["e:calls:test:1277","e:calls:test:1784","e:calls:console.error:1104"],"file":"archive/tetragrammatron-os/tests/unit/test_validate_jsonl.mjs","language":"mjs","pattern_id":"pi.conformance_surface.archive.tetragrammatron-os.tests.unit.test_validate_jsonl.mjs","pattern_type":"ConformanceSurface","source_frame_hash":"2e34af2413867bfc7c3a9730524a4be06a16966e2050f40fb9cac72e42b0dd7d","subject_nodes":["n:module"]},{"confidence":0.82,"evidence_edges":["e:calls:test:1267","e:calls:test:3014","e:calls:JSON.parse:2407"],"file":"tests/integration/test_pipeline.mjs","language":"mjs","pattern_id":"pi.conformance_surface.tests.integration.test_pipeline.mjs","pattern_type":"ConformanceSurface","source_frame_hash":"684245638ed3a42ef5f2d517fc1573d46e7f09c09c6f455b733877cf7ae3f672","subject_nodes":["n:module"]},{"confidence":0.82,"evidence_edges":["e:calls:runTest:918","e:calls:console.error:1152"],"file":"tests/run_all.mjs","language":"mjs","pattern_id":"pi.conformance_surface.tests.run_all.mjs","pattern_type":"ConformanceSurface","source_frame_hash":"7db9b48a4db33469f41e40ff4544da4623a0b6f1c114f15c2cdaecbe2c827e87","subject_nodes":["n:module"]},{"confidence":0.82,"evidence_edges":["e:calls:test:1212","e:calls:test:3943","e:calls:Array.isArray:2361"],"file":"tests/unit/test_gen_indexes.mjs","language":"mjs","pattern_id":"pi.conformance_surface.tests.unit.test_gen_indexes.mjs","pattern_type":"ConformanceSurface","source_frame_hash":"7464437d3777296ca52b46780da839f01b27f95a09447fc2104ae9f11f6b45a8","subject_nodes":["n:module"]},{"confidence":0.82,"evidence_edges":["e:calls:test:1195","e:calls:test:2322","e:calls:JSON.parse:1845"],"file":"tests/unit/test_hw_canon.mjs","language":"mjs","pattern_id":"pi.conformance_surface.tests.unit.test_hw_canon.mjs","pattern_type":"ConformanceSurface","source_frame_hash":"3214f98484fde0f4dcd25e3b77630fd7f248271faa5e3a93d54c651c8b58d0a4","subject_nodes":["n:module"]},{"confidence":0.82,"evidence_edges":["e:calls:test:1204","e:calls:test:2884","e:calls:JSON.parse:2186"],"file":"tests/unit/test_hw_project.mjs","language":"mjs","pattern_id":"pi.conformance_surface.tests.unit.test_hw_project.mjs","pattern_type":"ConformanceSurface","source_frame_hash":"4e1145aae7c626a63e7e5d0eee3f102c2a68fb72c82e7df2feb5e40f0dd6de97","subject_nodes":["n:module"]},{"confidence":0.82,"evidence_edges":["e:calls:test:1277","e:calls:test:1784","e:calls:console.error:1104"],"file":"tests/unit/test_validate_jsonl.mjs","language":"mjs","pattern_id":"pi.conformance_surface.tests.unit.test_validate_jsonl.mjs","pattern_type":"ConformanceSurface","source_frame_hash":"f78449d25bb9379a8ff628c013ea254d5b941d84fc2a1c0525a4d24f41a7dda3","subject_nodes":["n:module"]},{"confidence":0.8,"evidence_edges":["e:imports:esbuild:0"],"file":"archive/tetragrammatron-os/trees/obsidian/plugin/esbuild.config.mjs","language":"mjs","pattern_id":"pi.projection_only_surface.archive.tetragrammatron-os.trees.obsidian.plugin.esbuild.config.mjs","pattern_type":"ProjectionOnlySurface","source_frame_hash":"4d9f5a77109a71deba3524ebf22bd75df233a57c49724357dbd44a84c365f47f","subject_nodes":["n:module"]},{"confidence":0.8,"evidence_edges":["e:imports:esbuild:0"],"file":"trees/obsidian/plugin/esbuild.config.mjs","language":"mjs","pattern_id":"pi.projection_only_surface.trees.obsidian.plugin.esbuild.config.mjs","pattern_type":"ProjectionOnlySurface","source_frame_hash":"0a6afd44c6e291844e5207a4dd4f1f444f68b31d3b4378cf5e3143f8141379f7","subject_nodes":["n:module"]}],"outputs_digest":"sha256:4fc1d2f28c427dd62ae772d48c278bfe76861707de7a453342d09c7b07bbf6fb","summary":{"asg_edges":2717,"asg_nodes":3737,"domain_counts":{"carrier":6,"conformance":15,"core":12,"projection":2},"files":35,"language_counts":{"mjs":35},"patterns":{"BoundarySplit":4,"BridgeLayer":4,"CarrierLayer":14,"ConformanceSurface":12,"ProjectionOnlySurface":2}},"target":{"languages":["mjs"],"path":"/home/main/devops/tetragrammatron-os"},"v":"analysis-report.v0","warnings":[]}
