{"authority":"advisory","edges":[{"attrs":{},"from":"n:module","id":"e:calls:FractalizationSuperiorityExperiment:18952","kind":"Calls","symbol":"cp:Calls","to":"n:typeref:FractalizationSuperiorityExperiment"},{"attrs":{},"from":"n:module","id":"e:calls:Math.abs:8990","kind":"Calls","symbol":"cp:Calls","to":"n:typeref:Math.abs"},{"attrs":{},"from":"n:module","id":"e:calls:Math.exp:7788","kind":"Calls","symbol":"cp:Calls","to":"n:typeref:Math.exp"},{"attrs":{},"from":"n:module","id":"e:calls:Math.exp:8980","kind":"Calls","symbol":"cp:Calls","to":"n:typeref:Math.exp"},{"attrs":{},"from":"n:module","id":"e:calls:Math.log:8999","kind":"Calls","symbol":"cp:Calls","to":"n:typeref:Math.log"},{"attrs":{},"from":"n:module","id":"e:calls:Math.max:6607","kind":"Calls","symbol":"cp:Calls","to":"n:typeref:Math.max"},{"attrs":{},"from":"n:module","id":"e:calls:Math.max:6879","kind":"Calls","symbol":"cp:Calls","to":"n:typeref:Math.max"},{"attrs":{},"from":"n:module","id":"e:calls:Math.min:5677","kind":"Calls","symbol":"cp:Calls","to":"n:typeref:Math.min"},{"attrs":{},"from":"n:module","id":"e:calls:Math.min:6650","kind":"Calls","symbol":"cp:Calls","to":"n:typeref:Math.min"},{"attrs":{},"from":"n:module","id":"e:calls:Math.pow:7593","kind":"Calls","symbol":"cp:Calls","to":"n:typeref:Math.pow"},{"attrs":{},"from":"n:module","id":"e:calls:Math.pow:7649","kind":"Calls","symbol":"cp:Calls","to":"n:typeref:Math.pow"},{"attrs":{},"from":"n:module","id":"e:calls:Math.pow:7705","kind":"Calls","symbol":"cp:Calls","to":"n:typeref:Math.pow"},{"attrs":{},"from":"n:module","id":"e:calls:Math.sqrt:7572","kind":"Calls","symbol":"cp:Calls","to":"n:typeref:Math.sqrt"},{"attrs":{},"from":"n:module","id":"e:calls:MultiDimensionalEntityExperiment:9767","kind":"Calls","symbol":"cp:Calls","to":"n:typeref:MultiDimensionalEntityExperiment"},{"attrs":{},"from":"n:module","id":"e:calls:Object.values:8456","kind":"Calls","symbol":"cp:Calls","to":"n:typeref:Object.values"},{"attrs":{},"from":"n:module","id":"e:calls:PlatonicSolidExpansionExperiment:9837","kind":"Calls","symbol":"cp:Calls","to":"n:typeref:PlatonicSolidExpansionExperiment"},{"attrs":{},"from":"n:module","id":"e:calls:TraditionalFractalizationSimulator:9909","kind":"Calls","symbol":"cp:Calls","to":"n:typeref:TraditionalFractalizationSimulator"},{"attrs":{},"from":"n:module","id":"e:calls:VCSMFractalizationAnalyzer:9975","kind":"Calls","symbol":"cp:Calls","to":"n:typeref:VCSMFractalizationAnalyzer"},{"attrs":{},"from":"n:module","id":"e:calls:analyzeVCSMApproach:3259","kind":"Calls","symbol":"cp:Calls","to":"n:typeref:analyzeVCSMApproach"},{"attrs":{},"from":"n:module","id":"e:calls:calculateGeometricConsistency:7004","kind":"Calls","symbol":"cp:Calls","to":"n:typeref:calculateGeometricConsistency"},{"attrs":{},"from":"n:module","id":"e:calls:calculateKnowledgeDensity:5302","kind":"Calls","symbol":"cp:Calls","to":"n:typeref:calculateKnowledgeDensity"},{"attrs":{},"from":"n:module","id":"e:calls:calculateRepresentationDiversity:4466","kind":"Calls","symbol":"cp:Calls","to":"n:typeref:calculateRepresentationDiversity"},{"attrs":{},"from":"n:module","id":"e:calls:calculateSExpressionComplexity:5767","kind":"Calls","symbol":"cp:Calls","to":"n:typeref:calculateSExpressionComplexity"},{"attrs":{},"from":"n:module","id":"e:calls:calculateSExpressionDepth:6722","kind":"Calls","symbol":"cp:Calls","to":"n:typeref:calculateSExpressionDepth"},{"attrs":{},"from":"n:module","id":"e:calls:calculateScalabilityScore:7987","kind":"Calls","symbol":"cp:Calls","to":"n:typeref:calculateScalabilityScore"},{"attrs":{},"from":"n:module","id":"e:calls:console.log:10080","kind":"Calls","symbol":"cp:Calls","to":"n:typeref:console.log"},{"attrs":{},"from":"n:module","id":"e:calls:console.log:11263","kind":"Calls","symbol":"cp:Calls","to":"n:typeref:console.log"},{"attrs":{},"from":"n:module","id":"e:calls:console.log:11430","kind":"Calls","symbol":"cp:Calls","to":"n:typeref:console.log"},{"attrs":{},"from":"n:module","id":"e:calls:console.log:11625","kind":"Calls","symbol":"cp:Calls","to":"n:typeref:console.log"},{"attrs":{},"from":"n:module","id":"e:calls:console.log:11835","kind":"Calls","symbol":"cp:Calls","to":"n:typeref:console.log"},{"attrs":{},"from":"n:module","id":"e:calls:console.log:12993","kind":"Calls","symbol":"cp:Calls","to":"n:typeref:console.log"},{"attrs":{},"from":"n:module","id":"e:calls:console.log:13091","kind":"Calls","symbol":"cp:Calls","to":"n:typeref:console.log"},{"attrs":{},"from":"n:module","id":"e:calls:console.log:13189","kind":"Calls","symbol":"cp:Calls","to":"n:typeref:console.log"},{"attrs":{},"from":"n:module","id":"e:calls:console.log:13289","kind":"Calls","symbol":"cp:Calls","to":"n:typeref:console.log"},{"attrs":{},"from":"n:module","id":"e:calls:console.log:18859","kind":"Calls","symbol":"cp:Calls","to":"n:typeref:console.log"},{"attrs":{},"from":"n:module","id":"e:calls:console.log:19185","kind":"Calls","symbol":"cp:Calls","to":"n:typeref:console.log"},{"attrs":{},"from":"n:module","id":"e:calls:console.log:19227","kind":"Calls","symbol":"cp:Calls","to":"n:typeref:console.log"},{"attrs":{},"from":"n:module","id":"e:calls:console.log:19278","kind":"Calls","symbol":"cp:Calls","to":"n:typeref:console.log"},{"attrs":{},"from":"n:module","id":"e:calls:console.log:19313","kind":"Calls","symbol":"cp:Calls","to":"n:typeref:console.log"},{"attrs":{},"from":"n:module","id":"e:calls:console.log:19411","kind":"Calls","symbol":"cp:Calls","to":"n:typeref:console.log"},{"attrs":{},"from":"n:module","id":"e:calls:console.log:19511","kind":"Calls","symbol":"cp:Calls","to":"n:typeref:console.log"},{"attrs":{},"from":"n:module","id":"e:calls:constructor:9717","kind":"Calls","symbol":"cp:Calls","to":"n:typeref:constructor"},{"attrs":{},"from":"n:module","id":"e:calls:dimensionScores.push:8624","kind":"Calls","symbol":"cp:Calls","to":"n:typeref:dimensionScores.push"},{"attrs":{},"from":"n:module","id":"e:calls:dimensionScores.push:9034","kind":"Calls","symbol":"cp:Calls","to":"n:typeref:dimensionScores.push"},{"attrs":{},"from":"n:module","id":"e:calls:dimensionScores.reduce:9126","kind":"Calls","symbol":"cp:Calls","to":"n:typeref:dimensionScores.reduce"},{"attrs":{},"from":"n:module","id":"e:calls:duration.toFixed:13061","kind":"Calls","symbol":"cp:Calls","to":"n:typeref:duration.toFixed"},{"attrs":{},"from":"n:module","id":"e:calls:expansions.reduce:5528","kind":"Calls","symbol":"cp:Calls","to":"n:typeref:expansions.reduce"},{"attrs":{},"from":"n:module","id":"e:calls:expansions.reduce:6003","kind":"Calls","symbol":"cp:Calls","to":"n:typeref:expansions.reduce"},{"attrs":{},"from":"n:module","id":"e:calls:experiment.generateSuperiorityReport:19133","kind":"Calls","symbol":"cp:Calls","to":"n:typeref:experiment.generateSuperiorityReport"},{"attrs":{},"from":"n:module","id":"e:calls:experiment.runSuperiorityExperiment:19053","kind":"Calls","symbol":"cp:Calls","to":"n:typeref:experiment.runSuperiorityExperiment"},{"attrs":{},"from":"n:module","id":"e:calls:filter:8487","kind":"Calls","symbol":"cp:Calls","to":"n:typeref:filter"},{"attrs":{},"from":"n:module","id":"e:calls:generateSuperiorityReport:13487","kind":"Calls","symbol":"cp:Calls","to":"n:typeref:generateSuperiorityReport"},{"attrs":{},"from":"n:module","id":"e:calls:performance.now:10171","kind":"Calls","symbol":"cp:Calls","to":"n:typeref:performance.now"},{"attrs":{},"from":"n:module","id":"e:calls:performance.now:12923","kind":"Calls","symbol":"cp:Calls","to":"n:typeref:performance.now"},{"attrs":{},"from":"n:module","id":"e:calls:reasonable:8926","kind":"Calls","symbol":"cp:Calls","to":"n:typeref:reasonable"},{"attrs":{},"from":"n:module","id":"e:calls:results.reduce:5439","kind":"Calls","symbol":"cp:Calls","to":"n:typeref:results.reduce"},{"attrs":{},"from":"n:module","id":"e:calls:results.reduce:5914","kind":"Calls","symbol":"cp:Calls","to":"n:typeref:results.reduce"},{"attrs":{},"from":"n:module","id":"e:calls:runFractalizationSuperiorityExperiment:18814","kind":"Calls","symbol":"cp:Calls","to":"n:typeref:runFractalizationSuperiorityExperiment"},{"attrs":{},"from":"n:module","id":"e:calls:runFractalizationSuperiorityExperiment:19876","kind":"Calls","symbol":"cp:Calls","to":"n:typeref:runFractalizationSuperiorityExperiment"},{"attrs":{},"from":"n:module","id":"e:calls:runSuperiorityExperiment:10020","kind":"Calls","symbol":"cp:Calls","to":"n:typeref:runSuperiorityExperiment"},{"attrs":{},"from":"n:module","id":"e:calls:sExpr.children.map:6891","kind":"Calls","symbol":"cp:Calls","to":"n:typeref:sExpr.children.map"},{"attrs":{},"from":"n:module","id":"e:calls:simulateTraditionalApproach:2129","kind":"Calls","symbol":"cp:Calls","to":"n:typeref:simulateTraditionalApproach"},{"attrs":{},"from":"n:module","id":"e:calls:this.calculateGeometricConsistency:3843","kind":"Calls","symbol":"cp:Calls","to":"n:typeref:this.calculateGeometricConsistency"},{"attrs":{},"from":"n:module","id":"e:calls:this.calculateKnowledgeDensity:3575","kind":"Calls","symbol":"cp:Calls","to":"n:typeref:this.calculateKnowledgeDensity"},{"attrs":{},"from":"n:module","id":"e:calls:this.calculateRepresentationDiversity:3458","kind":"Calls","symbol":"cp:Calls","to":"n:typeref:this.calculateRepresentationDiversity"},{"attrs":{},"from":"n:module","id":"e:calls:this.calculateSExpressionComplexity:3708","kind":"Calls","symbol":"cp:Calls","to":"n:typeref:this.calculateSExpressionComplexity"},{"attrs":{},"from":"n:module","id":"e:calls:this.calculateSExpressionDepth:6331","kind":"Calls","symbol":"cp:Calls","to":"n:typeref:this.calculateSExpressionDepth"},{"attrs":{},"from":"n:module","id":"e:calls:this.calculateSExpressionDepth:6505","kind":"Calls","symbol":"cp:Calls","to":"n:typeref:this.calculateSExpressionDepth"},{"attrs":{},"from":"n:module","id":"e:calls:this.calculateSExpressionDepth:6926","kind":"Calls","symbol":"cp:Calls","to":"n:typeref:this.calculateSExpressionDepth"},{"attrs":{},"from":"n:module","id":"e:calls:this.calculateScalabilityScore:3957","kind":"Calls","symbol":"cp:Calls","to":"n:typeref:this.calculateScalabilityScore"},{"attrs":{},"from":"n:module","id":"e:calls:this.multiDimExperiment.runBatchExperiment:11367","kind":"Calls","symbol":"cp:Calls","to":"n:typeref:this.multiDimExperiment.runBatchExperiment"},{"attrs":{},"from":"n:module","id":"e:calls:this.platonicExperiment.runExpansionExperiment:11537","kind":"Calls","symbol":"cp:Calls","to":"n:typeref:this.platonicExperiment.runExpansionExperiment"},{"attrs":{},"from":"n:module","id":"e:calls:this.traditionalSimulator.simulateTraditionalApproach:11919","kind":"Calls","symbol":"cp:Calls","to":"n:typeref:this.traditionalSimulator.simulateTraditionalApproach"},{"attrs":{},"from":"n:module","id":"e:calls:this.vcsmAnalyzer.analyzeVCSMApproach:11713","kind":"Calls","symbol":"cp:Calls","to":"n:typeref:this.vcsmAnalyzer.analyzeVCSMApproach"},{"attrs":{},"from":"n:module","id":"e:calls:toFixed:13169","kind":"Calls","symbol":"cp:Calls","to":"n:typeref:toFixed"},{"attrs":{},"from":"n:module","id":"e:calls:toFixed:13269","kind":"Calls","symbol":"cp:Calls","to":"n:typeref:toFixed"},{"attrs":{},"from":"n:module","id":"e:calls:toFixed:13355","kind":"Calls","symbol":"cp:Calls","to":"n:typeref:toFixed"},{"attrs":{},"from":"n:module","id":"e:calls:toFixed:13757","kind":"Calls","symbol":"cp:Calls","to":"n:typeref:toFixed"},{"attrs":{},"from":"n:module","id":"e:calls:toFixed:13864","kind":"Calls","symbol":"cp:Calls","to":"n:typeref:toFixed"},{"attrs":{},"from":"n:module","id":"e:calls:toFixed:13964","kind":"Calls","symbol":"cp:Calls","to":"n:typeref:toFixed"},{"attrs":{},"from":"n:module","id":"e:calls:toFixed:14170","kind":"Calls","symbol":"cp:Calls","to":"n:typeref:toFixed"},{"attrs":{},"from":"n:module","id":"e:calls:toFixed:14278","kind":"Calls","symbol":"cp:Calls","to":"n:typeref:toFixed"},{"attrs":{},"from":"n:module","id":"e:calls:toFixed:14386","kind":"Calls","symbol":"cp:Calls","to":"n:typeref:toFixed"},{"attrs":{},"from":"n:module","id":"e:calls:toFixed:14521","kind":"Calls","symbol":"cp:Calls","to":"n:typeref:toFixed"},{"attrs":{},"from":"n:module","id":"e:calls:toFixed:14622","kind":"Calls","symbol":"cp:Calls","to":"n:typeref:toFixed"},{"attrs":{},"from":"n:module","id":"e:calls:toFixed:14723","kind":"Calls","symbol":"cp:Calls","to":"n:typeref:toFixed"},{"attrs":{},"from":"n:module","id":"e:calls:toFixed:14869","kind":"Calls","symbol":"cp:Calls","to":"n:typeref:toFixed"},{"attrs":{},"from":"n:module","id":"e:calls:toFixed:14975","kind":"Calls","symbol":"cp:Calls","to":"n:typeref:toFixed"},{"attrs":{},"from":"n:module","id":"e:calls:toFixed:15081","kind":"Calls","symbol":"cp:Calls","to":"n:typeref:toFixed"},{"attrs":{},"from":"n:module","id":"e:calls:toFixed:15224","kind":"Calls","symbol":"cp:Calls","to":"n:typeref:toFixed"},{"attrs":{},"from":"n:module","id":"e:calls:toFixed:15329","kind":"Calls","symbol":"cp:Calls","to":"n:typeref:toFixed"},{"attrs":{},"from":"n:module","id":"e:calls:toFixed:15434","kind":"Calls","symbol":"cp:Calls","to":"n:typeref:toFixed"},{"attrs":{},"from":"n:module","id":"e:calls:toFixed:15569","kind":"Calls","symbol":"cp:Calls","to":"n:typeref:toFixed"},{"attrs":{},"from":"n:module","id":"e:calls:toFixed:15670","kind":"Calls","symbol":"cp:Calls","to":"n:typeref:toFixed"},{"attrs":{},"from":"n:module","id":"e:calls:toFixed:15771","kind":"Calls","symbol":"cp:Calls","to":"n:typeref:toFixed"},{"attrs":{},"from":"n:module","id":"e:calls:toFixed:16225","kind":"Calls","symbol":"cp:Calls","to":"n:typeref:toFixed"},{"attrs":{},"from":"n:module","id":"e:calls:toFixed:16639","kind":"Calls","symbol":"cp:Calls","to":"n:typeref:toFixed"},{"attrs":{},"from":"n:module","id":"e:calls:toFixed:17029","kind":"Calls","symbol":"cp:Calls","to":"n:typeref:toFixed"},{"attrs":{},"from":"n:module","id":"e:calls:toFixed:17431","kind":"Calls","symbol":"cp:Calls","to":"n:typeref:toFixed"},{"attrs":{},"from":"n:module","id":"e:calls:toFixed:17799","kind":"Calls","symbol":"cp:Calls","to":"n:typeref:toFixed"},{"attrs":{},"from":"n:module","id":"e:calls:toFixed:17993","kind":"Calls","symbol":"cp:Calls","to":"n:typeref:toFixed"},{"attrs":{},"from":"n:module","id":"e:calls:toFixed:19393","kind":"Calls","symbol":"cp:Calls","to":"n:typeref:toFixed"},{"attrs":{},"from":"n:module","id":"e:calls:toFixed:19493","kind":"Calls","symbol":"cp:Calls","to":"n:typeref:toFixed"},{"attrs":{},"from":"n:module","id":"e:calls:toFixed:19586","kind":"Calls","symbol":"cp:Calls","to":"n:typeref:toFixed"},{"attrs":{},"from":"n:module","id":"e:calls:uniqueRepresentations.add:4776","kind":"Calls","symbol":"cp:Calls","to":"n:typeref:uniqueRepresentations.add"},{"attrs":{},"from":"n:module","id":"e:calls:uniqueRepresentations.add:4852","kind":"Calls","symbol":"cp:Calls","to":"n:typeref:uniqueRepresentations.add"},{"attrs":{},"from":"n:module","id":"e:calls:uniqueRepresentations.add:4930","kind":"Calls","symbol":"cp:Calls","to":"n:typeref:uniqueRepresentations.add"},{"attrs":{},"from":"n:module","id":"e:calls:uniqueRepresentations.add:5010","kind":"Calls","symbol":"cp:Calls","to":"n:typeref:uniqueRepresentations.add"},{"attrs":{},"from":"n:module","id":"e:calls:uniqueRepresentations.add:5089","kind":"Calls","symbol":"cp:Calls","to":"n:typeref:uniqueRepresentations.add"},{"attrs":{},"from":"n:module","id":"e:calls:uniqueRepresentations.add:5169","kind":"Calls","symbol":"cp:Calls","to":"n:typeref:uniqueRepresentations.add"},{"attrs":{},"from":"n:module","id":"e:defines:class:FractalizationSuperiorityExperiment","kind":"Defines","symbol":"cp:Defines","to":"n:class:FractalizationSuperiorityExperiment"},{"attrs":{},"from":"n:module","id":"e:defines:class:TraditionalFractalizationSimulator","kind":"Defines","symbol":"cp:Defines","to":"n:class:TraditionalFractalizationSimulator"},{"attrs":{},"from":"n:module","id":"e:defines:class:VCSMFractalizationAnalyzer","kind":"Defines","symbol":"cp:Defines","to":"n:class:VCSMFractalizationAnalyzer"},{"attrs":{},"from":"n:module","id":"e:defines:method:constructor:9712","kind":"Defines","symbol":"cp:Defines","to":"n:method:constructor"},{"attrs":{},"from":"n:module","id":"e:imports:perf_hooks:585","kind":"Imports","symbol":"cp:Imports","to":"n:import:perf_hooks"}],"graph_hash":"sha256:f1c4f36de882987a880e5b4512e5598d1ee5c9d7159fe1f28df4787e5ceadd75","language":"typescript","namespace":"analysis.typescript.packages.vector-clock-state-engine.experiments.src.fractalization-superiority-experiment.ts","nodes":[{"attrs":{"name":"FractalizationSuperiorityExperiment"},"id":"n:class:FractalizationSuperiorityExperiment","kind":"Class","source":{"column":0,"end_column":42,"end_line":238,"line":237,"path":"packages/vector-clock-state-engine/experiments/src/fractalization-superiority-experiment.ts"},"symbol":"cp:Class"},{"attrs":{"name":"TraditionalFractalizationSimulator"},"id":"n:class:TraditionalFractalizationSimulator","kind":"Class","source":{"column":0,"end_column":41,"end_line":57,"line":56,"path":"packages/vector-clock-state-engine/experiments/src/fractalization-superiority-experiment.ts"},"symbol":"cp:Class"},{"attrs":{"name":"VCSMFractalizationAnalyzer"},"id":"n:class:VCSMFractalizationAnalyzer","kind":"Class","source":{"column":0,"end_column":33,"end_line":89,"line":88,"path":"packages/vector-clock-state-engine/experiments/src/fractalization-superiority-experiment.ts"},"symbol":"cp:Class"},{"attrs":{"name":"perf_hooks"},"id":"n:import:perf_hooks","kind":"Namespace","source":{"column":0,"end_column":41,"end_line":16,"line":15,"path":"packages/vector-clock-state-engine/experiments/src/fractalization-superiority-experiment.ts"},"symbol":"cp:Namespace"},{"attrs":{"name":"constructor"},"id":"n:method:constructor","kind":"Method","source":{"column":0,"end_column":17,"end_line":244,"line":243,"path":"packages/vector-clock-state-engine/experiments/src/fractalization-superiority-experiment.ts"},"symbol":"cp:Method"},{"attrs":{"name":"packages/vector-clock-state-engine/experiments/src/fractalization-superiority-experiment.ts"},"id":"n:module","kind":"Module","source":{"column":0,"end_column":1,"end_line":457,"line":1,"path":"packages/vector-clock-state-engine/experiments/src/fractalization-superiority-experiment.ts"},"symbol":"cp:Module"},{"attrs":{"name":"FractalizationSuperiorityExperiment"},"id":"n:typeref:FractalizationSuperiorityExperiment","kind":"TypeRef","source":{"column":25,"end_column":61,"end_line":427,"line":427,"path":"packages/vector-clock-state-engine/experiments/src/fractalization-superiority-experiment.ts"},"symbol":"cp:TypeRef"},{"attrs":{"name":"Math.abs"},"id":"n:typeref:Math.abs","kind":"TypeRef","source":{"column":35,"end_column":44,"end_line":225,"line":225,"path":"packages/vector-clock-state-engine/experiments/src/fractalization-superiority-experiment.ts"},"symbol":"cp:TypeRef"},{"attrs":{"name":"Math.exp"},"id":"n:typeref:Math.exp","kind":"TypeRef","source":{"column":28,"end_column":37,"end_line":196,"line":196,"path":"packages/vector-clock-state-engine/experiments/src/fractalization-superiority-experiment.ts"},"symbol":"cp:TypeRef"},{"attrs":{"name":"Math.log"},"id":"n:typeref:Math.log","kind":"TypeRef","source":{"column":44,"end_column":53,"end_line":225,"line":225,"path":"packages/vector-clock-state-engine/experiments/src/fractalization-superiority-experiment.ts"},"symbol":"cp:TypeRef"},{"attrs":{"name":"Math.max"},"id":"n:typeref:Math.max","kind":"TypeRef","source":{"column":44,"end_column":53,"end_line":167,"line":167,"path":"packages/vector-clock-state-engine/experiments/src/fractalization-superiority-experiment.ts"},"symbol":"cp:TypeRef"},{"attrs":{"name":"Math.min"},"id":"n:typeref:Math.min","kind":"TypeRef","source":{"column":11,"end_column":20,"end_line":146,"line":146,"path":"packages/vector-clock-state-engine/experiments/src/fractalization-superiority-experiment.ts"},"symbol":"cp:TypeRef"},{"attrs":{"name":"Math.pow"},"id":"n:typeref:Math.pow","kind":"TypeRef","source":{"column":10,"end_column":19,"end_line":192,"line":192,"path":"packages/vector-clock-state-engine/experiments/src/fractalization-superiority-experiment.ts"},"symbol":"cp:TypeRef"},{"attrs":{"name":"Math.sqrt"},"id":"n:typeref:Math.sqrt","kind":"TypeRef","source":{"column":25,"end_column":35,"end_line":191,"line":191,"path":"packages/vector-clock-state-engine/experiments/src/fractalization-superiority-experiment.ts"},"symbol":"cp:TypeRef"},{"attrs":{"name":"MultiDimensionalEntityExperiment"},"id":"n:typeref:MultiDimensionalEntityExperiment","kind":"TypeRef","source":{"column":34,"end_column":67,"end_line":245,"line":245,"path":"packages/vector-clock-state-engine/experiments/src/fractalization-superiority-experiment.ts"},"symbol":"cp:TypeRef"},{"attrs":{"name":"Object.values"},"id":"n:typeref:Object.values","kind":"TypeRef","source":{"column":34,"end_column":48,"end_line":213,"line":213,"path":"packages/vector-clock-state-engine/experiments/src/fractalization-superiority-experiment.ts"},"symbol":"cp:TypeRef"},{"attrs":{"name":"PlatonicSolidExpansionExperiment"},"id":"n:typeref:PlatonicSolidExpansionExperiment","kind":"TypeRef","source":{"column":34,"end_column":67,"end_line":246,"line":246,"path":"packages/vector-clock-state-engine/experiments/src/fractalization-superiority-experiment.ts"},"symbol":"cp:TypeRef"},{"attrs":{"name":"TraditionalFractalizationSimulator"},"id":"n:typeref:TraditionalFractalizationSimulator","kind":"TypeRef","source":{"column":36,"end_column":71,"end_line":247,"line":247,"path":"packages/vector-clock-state-engine/experiments/src/fractalization-superiority-experiment.ts"},"symbol":"cp:TypeRef"},{"attrs":{"name":"VCSMFractalizationAnalyzer"},"id":"n:typeref:VCSMFractalizationAnalyzer","kind":"TypeRef","source":{"column":28,"end_column":55,"end_line":248,"line":248,"path":"packages/vector-clock-state-engine/experiments/src/fractalization-superiority-experiment.ts"},"symbol":"cp:TypeRef"},{"attrs":{"name":"analyzeVCSMApproach"},"id":"n:typeref:analyzeVCSMApproach","kind":"TypeRef","source":{"column":2,"end_column":22,"end_line":90,"line":90,"path":"packages/vector-clock-state-engine/experiments/src/fractalization-superiority-experiment.ts"},"symbol":"cp:TypeRef"},{"attrs":{"name":"calculateGeometricConsistency"},"id":"n:typeref:calculateGeometricConsistency","kind":"TypeRef","source":{"column":10,"end_column":40,"end_line":179,"line":179,"path":"packages/vector-clock-state-engine/experiments/src/fractalization-superiority-experiment.ts"},"symbol":"cp:TypeRef"},{"attrs":{"name":"calculateKnowledgeDensity"},"id":"n:typeref:calculateKnowledgeDensity","kind":"TypeRef","source":{"column":10,"end_column":36,"end_line":141,"line":141,"path":"packages/vector-clock-state-engine/experiments/src/fractalization-superiority-experiment.ts"},"symbol":"cp:TypeRef"},{"attrs":{"name":"calculateRepresentationDiversity"},"id":"n:typeref:calculateRepresentationDiversity","kind":"TypeRef","source":{"column":10,"end_column":43,"end_line":125,"line":125,"path":"packages/vector-clock-state-engine/experiments/src/fractalization-superiority-experiment.ts"},"symbol":"cp:TypeRef"},{"attrs":{"name":"calculateSExpressionComplexity"},"id":"n:typeref:calculateSExpressionComplexity","kind":"TypeRef","source":{"column":10,"end_column":41,"end_line":149,"line":149,"path":"packages/vector-clock-state-engine/experiments/src/fractalization-superiority-experiment.ts"},"symbol":"cp:TypeRef"},{"attrs":{"name":"calculateSExpressionDepth"},"id":"n:typeref:calculateSExpressionDepth","kind":"TypeRef","source":{"column":10,"end_column":36,"end_line":171,"line":171,"path":"packages/vector-clock-state-engine/experiments/src/fractalization-superiority-experiment.ts"},"symbol":"cp:TypeRef"},{"attrs":{"name":"calculateScalabilityScore"},"id":"n:typeref:calculateScalabilityScore","kind":"TypeRef","source":{"column":10,"end_column":36,"end_line":204,"line":204,"path":"packages/vector-clock-state-engine/experiments/src/fractalization-superiority-experiment.ts"},"symbol":"cp:TypeRef"},{"attrs":{"name":"console.log"},"id":"n:typeref:console.log","kind":"TypeRef","source":{"column":4,"end_column":16,"end_line":252,"line":252,"path":"packages/vector-clock-state-engine/experiments/src/fractalization-superiority-experiment.ts"},"symbol":"cp:TypeRef"},{"attrs":{"name":"constructor"},"id":"n:typeref:constructor","kind":"TypeRef","source":{"column":2,"end_column":14,"end_line":244,"line":244,"path":"packages/vector-clock-state-engine/experiments/src/fractalization-superiority-experiment.ts"},"symbol":"cp:TypeRef"},{"attrs":{"name":"dimensionScores.push"},"id":"n:typeref:dimensionScores.push","kind":"TypeRef","source":{"column":6,"end_column":27,"end_line":216,"line":216,"path":"packages/vector-clock-state-engine/experiments/src/fractalization-superiority-experiment.ts"},"symbol":"cp:TypeRef"},{"attrs":{"name":"dimensionScores.reduce"},"id":"n:typeref:dimensionScores.reduce","kind":"TypeRef","source":{"column":6,"end_column":29,"end_line":230,"line":230,"path":"packages/vector-clock-state-engine/experiments/src/fractalization-superiority-experiment.ts"},"symbol":"cp:TypeRef"},{"attrs":{"name":"duration.toFixed"},"id":"n:typeref:duration.toFixed","kind":"TypeRef","source":{"column":72,"end_column":89,"end_line":323,"line":323,"path":"packages/vector-clock-state-engine/experiments/src/fractalization-superiority-experiment.ts"},"symbol":"cp:TypeRef"},{"attrs":{"name":"expansions.reduce"},"id":"n:typeref:expansions.reduce","kind":"TypeRef","source":{"column":24,"end_column":42,"end_line":143,"line":143,"path":"packages/vector-clock-state-engine/experiments/src/fractalization-superiority-experiment.ts"},"symbol":"cp:TypeRef"},{"attrs":{"name":"experiment.generateSuperiorityReport"},"id":"n:typeref:experiment.generateSuperiorityReport","kind":"TypeRef","source":{"column":17,"end_column":54,"end_line":433,"line":433,"path":"packages/vector-clock-state-engine/experiments/src/fractalization-superiority-experiment.ts"},"symbol":"cp:TypeRef"},{"attrs":{"name":"experiment.runSuperiorityExperiment"},"id":"n:typeref:experiment.runSuperiorityExperiment","kind":"TypeRef","source":{"column":27,"end_column":63,"end_line":430,"line":430,"path":"packages/vector-clock-state-engine/experiments/src/fractalization-superiority-experiment.ts"},"symbol":"cp:TypeRef"},{"attrs":{"name":"filter"},"id":"n:typeref:filter","kind":"TypeRef","source":{"column":65,"end_column":72,"end_line":213,"line":213,"path":"packages/vector-clock-state-engine/experiments/src/fractalization-superiority-experiment.ts"},"symbol":"cp:TypeRef"},{"attrs":{"name":"generateSuperiorityReport"},"id":"n:typeref:generateSuperiorityReport","kind":"TypeRef","source":{"column":2,"end_column":28,"end_line":335,"line":335,"path":"packages/vector-clock-state-engine/experiments/src/fractalization-superiority-experiment.ts"},"symbol":"cp:TypeRef"},{"attrs":{"name":"performance.now"},"id":"n:typeref:performance.now","kind":"TypeRef","source":{"column":22,"end_column":38,"end_line":254,"line":254,"path":"packages/vector-clock-state-engine/experiments/src/fractalization-superiority-experiment.ts"},"symbol":"cp:TypeRef"},{"attrs":{"name":"reasonable"},"id":"n:typeref:reasonable","kind":"TypeRef","source":{"column":40,"end_column":52,"end_line":224,"line":224,"path":"packages/vector-clock-state-engine/experiments/src/fractalization-superiority-experiment.ts"},"symbol":"cp:TypeRef"},{"attrs":{"name":"results.reduce"},"id":"n:typeref:results.reduce","kind":"TypeRef","source":{"column":25,"end_column":40,"end_line":142,"line":142,"path":"packages/vector-clock-state-engine/experiments/src/fractalization-superiority-experiment.ts"},"symbol":"cp:TypeRef"},{"attrs":{"name":"runFractalizationSuperiorityExperiment"},"id":"n:typeref:runFractalizationSuperiorityExperiment","kind":"TypeRef","source":{"column":15,"end_column":54,"end_line":424,"line":424,"path":"packages/vector-clock-state-engine/experiments/src/fractalization-superiority-experiment.ts"},"symbol":"cp:TypeRef"},{"attrs":{"name":"runSuperiorityExperiment"},"id":"n:typeref:runSuperiorityExperiment","kind":"TypeRef","source":{"column":8,"end_column":33,"end_line":251,"line":251,"path":"packages/vector-clock-state-engine/experiments/src/fractalization-superiority-experiment.ts"},"symbol":"cp:TypeRef"},{"attrs":{"name":"sExpr.children.map"},"id":"n:typeref:sExpr.children.map","kind":"TypeRef","source":{"column":29,"end_column":48,"end_line":174,"line":174,"path":"packages/vector-clock-state-engine/experiments/src/fractalization-superiority-experiment.ts"},"symbol":"cp:TypeRef"},{"attrs":{"name":"simulateTraditionalApproach"},"id":"n:typeref:simulateTraditionalApproach","kind":"TypeRef","source":{"column":2,"end_column":30,"end_line":58,"line":58,"path":"packages/vector-clock-state-engine/experiments/src/fractalization-superiority-experiment.ts"},"symbol":"cp:TypeRef"},{"attrs":{"name":"this.calculateGeometricConsistency"},"id":"n:typeref:this.calculateGeometricConsistency","kind":"TypeRef","source":{"column":33,"end_column":68,"end_line":101,"line":101,"path":"packages/vector-clock-state-engine/experiments/src/fractalization-superiority-experiment.ts"},"symbol":"cp:TypeRef"},{"attrs":{"name":"this.calculateKnowledgeDensity"},"id":"n:typeref:this.calculateKnowledgeDensity","kind":"TypeRef","source":{"column":29,"end_column":60,"end_line":95,"line":95,"path":"packages/vector-clock-state-engine/experiments/src/fractalization-superiority-experiment.ts"},"symbol":"cp:TypeRef"},{"attrs":{"name":"this.calculateRepresentationDiversity"},"id":"n:typeref:this.calculateRepresentationDiversity","kind":"TypeRef","source":{"column":36,"end_column":74,"end_line":92,"line":92,"path":"packages/vector-clock-state-engine/experiments/src/fractalization-superiority-experiment.ts"},"symbol":"cp:TypeRef"},{"attrs":{"name":"this.calculateSExpressionComplexity"},"id":"n:typeref:this.calculateSExpressionComplexity","kind":"TypeRef","source":{"column":34,"end_column":70,"end_line":98,"line":98,"path":"packages/vector-clock-state-engine/experiments/src/fractalization-superiority-experiment.ts"},"symbol":"cp:TypeRef"},{"attrs":{"name":"this.calculateSExpressionDepth"},"id":"n:typeref:this.calculateSExpressionDepth","kind":"TypeRef","source":{"column":27,"end_column":58,"end_line":158,"line":158,"path":"packages/vector-clock-state-engine/experiments/src/fractalization-superiority-experiment.ts"},"symbol":"cp:TypeRef"},{"attrs":{"name":"this.calculateScalabilityScore"},"id":"n:typeref:this.calculateScalabilityScore","kind":"TypeRef","source":{"column":29,"end_column":60,"end_line":104,"line":104,"path":"packages/vector-clock-state-engine/experiments/src/fractalization-superiority-experiment.ts"},"symbol":"cp:TypeRef"},{"attrs":{"name":"this.multiDimExperiment.runBatchExperiment"},"id":"n:typeref:this.multiDimExperiment.runBatchExperiment","kind":"TypeRef","source":{"column":34,"end_column":77,"end_line":297,"line":297,"path":"packages/vector-clock-state-engine/experiments/src/fractalization-superiority-experiment.ts"},"symbol":"cp:TypeRef"},{"attrs":{"name":"this.platonicExperiment.runExpansionExperiment"},"id":"n:typeref:this.platonicExperiment.runExpansionExperiment","kind":"TypeRef","source":{"column":37,"end_column":84,"end_line":300,"line":300,"path":"packages/vector-clock-state-engine/experiments/src/fractalization-superiority-experiment.ts"},"symbol":"cp:TypeRef"},{"attrs":{"name":"this.traditionalSimulator.simulateTraditionalApproach"},"id":"n:typeref:this.traditionalSimulator.simulateTraditionalApproach","kind":"TypeRef","source":{"column":31,"end_column":85,"end_line":308,"line":308,"path":"packages/vector-clock-state-engine/experiments/src/fractalization-superiority-experiment.ts"},"symbol":"cp:TypeRef"},{"attrs":{"name":"this.vcsmAnalyzer.analyzeVCSMApproach"},"id":"n:typeref:this.vcsmAnalyzer.analyzeVCSMApproach","kind":"TypeRef","source":{"column":24,"end_column":62,"end_line":304,"line":304,"path":"packages/vector-clock-state-engine/experiments/src/fractalization-superiority-experiment.ts"},"symbol":"cp:TypeRef"},{"attrs":{"name":"toFixed"},"id":"n:typeref:toFixed","kind":"TypeRef","source":{"column":82,"end_column":90,"end_line":324,"line":324,"path":"packages/vector-clock-state-engine/experiments/src/fractalization-superiority-experiment.ts"},"symbol":"cp:TypeRef"},{"attrs":{"name":"uniqueRepresentations.add"},"id":"n:typeref:uniqueRepresentations.add","kind":"TypeRef","source":{"column":40,"end_column":66,"end_line":130,"line":130,"path":"packages/vector-clock-state-engine/experiments/src/fractalization-superiority-experiment.ts"},"symbol":"cp:TypeRef"}],"provenance":{"parser":"typescript-regex","parser_version":"v0","source_path":"packages/vector-clock-state-engine/experiments/src/fractalization-superiority-experiment.ts"},"v":"ak.asg.v0"}
