{"authority":"advisory","edges":[],"graph_hash":"sha256:281725641a5aa781dd812417af9bff1a5b00018feb73a75452445195cd6dca49","language":"typescript","namespace":"analysis.typescript.ui.src.components.VirtualWorld.index.ts","nodes":[{"attrs":{"name":"ui/src/components/VirtualWorld/index.ts"},"id":"n:module","kind":"Module","source":{"column":0,"end_column":88,"end_line":112,"line":1,"path":"ui/src/components/VirtualWorld/index.ts"},"symbol":"cp:Module"}],"provenance":{"parser":"typescript-regex","parser_version":"v0","source_path":"ui/src/components/VirtualWorld/index.ts"},"v":"ak.asg.v0"}
