{"authority":"advisory","edges":[],"graph_hash":"sha256:7271c679f6e7b6d95f02bbb049512ad0083960c5ba313d728d63122d55b5c9a3","language":"typescript","namespace":"analysis.typescript.src.database.index.ts","nodes":[{"attrs":{"name":"src/database/index.ts"},"id":"n:module","kind":"Module","source":{"column":0,"end_column":41,"end_line":7,"line":1,"path":"src/database/index.ts"},"symbol":"cp:Module"}],"provenance":{"parser":"typescript-regex","parser_version":"v0","source_path":"src/database/index.ts"},"v":"ak.asg.v0"}
