{"authority":"advisory","edges":[{"attrs":{},"from":"n:module","id":"e:calls:authenticate:1035","kind":"Calls","symbol":"cp:Calls","to":"n:typeref:authenticate"},{"attrs":{},"from":"n:module","id":"e:calls:authorize:1098","kind":"Calls","symbol":"cp:Calls","to":"n:typeref:authorize"},{"attrs":{},"from":"n:module","id":"e:calls:compressMemory:972","kind":"Calls","symbol":"cp:Calls","to":"n:typeref:compressMemory"},{"attrs":{},"from":"n:module","id":"e:calls:consolidateMemory:934","kind":"Calls","symbol":"cp:Calls","to":"n:typeref:consolidateMemory"},{"attrs":{},"from":"n:module","id":"e:calls:createIdentity:573","kind":"Calls","symbol":"cp:Calls","to":"n:typeref:createIdentity"},{"attrs":{},"from":"n:module","id":"e:calls:decrypt:1227","kind":"Calls","symbol":"cp:Calls","to":"n:typeref:decrypt"},{"attrs":{},"from":"n:module","id":"e:calls:deleteIdentity:712","kind":"Calls","symbol":"cp:Calls","to":"n:typeref:deleteIdentity"},{"attrs":{},"from":"n:module","id":"e:calls:encrypt:1181","kind":"Calls","symbol":"cp:Calls","to":"n:typeref:encrypt"},{"attrs":{},"from":"n:module","id":"e:calls:getHealth:507","kind":"Calls","symbol":"cp:Calls","to":"n:typeref:getHealth"},{"attrs":{},"from":"n:module","id":"e:calls:getIdentity:757","kind":"Calls","symbol":"cp:Calls","to":"n:typeref:getIdentity"},{"attrs":{},"from":"n:module","id":"e:calls:getStatus:469","kind":"Calls","symbol":"cp:Calls","to":"n:typeref:getStatus"},{"attrs":{},"from":"n:module","id":"e:calls:initialize:409","kind":"Calls","symbol":"cp:Calls","to":"n:typeref:initialize"},{"attrs":{},"from":"n:module","id":"e:calls:retrieveMemory:877","kind":"Calls","symbol":"cp:Calls","to":"n:typeref:retrieveMemory"},{"attrs":{},"from":"n:module","id":"e:calls:shutdown:440","kind":"Calls","symbol":"cp:Calls","to":"n:typeref:shutdown"},{"attrs":{},"from":"n:module","id":"e:calls:storeMemory:831","kind":"Calls","symbol":"cp:Calls","to":"n:typeref:storeMemory"},{"attrs":{},"from":"n:module","id":"e:calls:updateIdentity:636","kind":"Calls","symbol":"cp:Calls","to":"n:typeref:updateIdentity"},{"attrs":{},"from":"n:module","id":"e:imports:../types/identity:93","kind":"Imports","symbol":"cp:Imports","to":"n:import:../types/identity"},{"attrs":{},"from":"n:module","id":"e:imports:../types/memory:142","kind":"Imports","symbol":"cp:Imports","to":"n:import:../types/memory"},{"attrs":{},"from":"n:module","id":"e:imports:../types/security:190","kind":"Imports","symbol":"cp:Imports","to":"n:import:../types/security"}],"graph_hash":"sha256:32eba9590a41ef13502db124fd257618e9ac3b72b5ac6b9e3880b1daa02b82c0","language":"typescript","namespace":"analysis.typescript.packages.autonomous-identity.core.src.interfaces.AIPersistenceCore.ts","nodes":[{"attrs":{"name":"../types/identity"},"id":"n:import:../types/identity","kind":"Namespace","source":{"column":0,"end_column":47,"end_line":7,"line":6,"path":"packages/autonomous-identity/core/src/interfaces/AIPersistenceCore.ts"},"symbol":"cp:Namespace"},{"attrs":{"name":"../types/memory"},"id":"n:import:../types/memory","kind":"Namespace","source":{"column":0,"end_column":47,"end_line":8,"line":8,"path":"packages/autonomous-identity/core/src/interfaces/AIPersistenceCore.ts"},"symbol":"cp:Namespace"},{"attrs":{"name":"../types/security"},"id":"n:import:../types/security","kind":"Namespace","source":{"column":0,"end_column":54,"end_line":9,"line":9,"path":"packages/autonomous-identity/core/src/interfaces/AIPersistenceCore.ts"},"symbol":"cp:Namespace"},{"attrs":{"name":"packages/autonomous-identity/core/src/interfaces/AIPersistenceCore.ts"},"id":"n:module","kind":"Module","source":{"column":0,"end_column":1,"end_line":295,"line":1,"path":"packages/autonomous-identity/core/src/interfaces/AIPersistenceCore.ts"},"symbol":"cp:Module"},{"attrs":{"name":"authenticate"},"id":"n:typeref:authenticate","kind":"TypeRef","source":{"column":2,"end_column":15,"end_line":36,"line":36,"path":"packages/autonomous-identity/core/src/interfaces/AIPersistenceCore.ts"},"symbol":"cp:TypeRef"},{"attrs":{"name":"authorize"},"id":"n:typeref:authorize","kind":"TypeRef","source":{"column":2,"end_column":12,"end_line":37,"line":37,"path":"packages/autonomous-identity/core/src/interfaces/AIPersistenceCore.ts"},"symbol":"cp:TypeRef"},{"attrs":{"name":"compressMemory"},"id":"n:typeref:compressMemory","kind":"TypeRef","source":{"column":2,"end_column":17,"end_line":33,"line":33,"path":"packages/autonomous-identity/core/src/interfaces/AIPersistenceCore.ts"},"symbol":"cp:TypeRef"},{"attrs":{"name":"consolidateMemory"},"id":"n:typeref:consolidateMemory","kind":"TypeRef","source":{"column":2,"end_column":20,"end_line":32,"line":32,"path":"packages/autonomous-identity/core/src/interfaces/AIPersistenceCore.ts"},"symbol":"cp:TypeRef"},{"attrs":{"name":"createIdentity"},"id":"n:typeref:createIdentity","kind":"TypeRef","source":{"column":2,"end_column":17,"end_line":24,"line":24,"path":"packages/autonomous-identity/core/src/interfaces/AIPersistenceCore.ts"},"symbol":"cp:TypeRef"},{"attrs":{"name":"decrypt"},"id":"n:typeref:decrypt","kind":"TypeRef","source":{"column":2,"end_column":10,"end_line":39,"line":39,"path":"packages/autonomous-identity/core/src/interfaces/AIPersistenceCore.ts"},"symbol":"cp:TypeRef"},{"attrs":{"name":"deleteIdentity"},"id":"n:typeref:deleteIdentity","kind":"TypeRef","source":{"column":2,"end_column":17,"end_line":26,"line":26,"path":"packages/autonomous-identity/core/src/interfaces/AIPersistenceCore.ts"},"symbol":"cp:TypeRef"},{"attrs":{"name":"encrypt"},"id":"n:typeref:encrypt","kind":"TypeRef","source":{"column":2,"end_column":10,"end_line":38,"line":38,"path":"packages/autonomous-identity/core/src/interfaces/AIPersistenceCore.ts"},"symbol":"cp:TypeRef"},{"attrs":{"name":"getHealth"},"id":"n:typeref:getHealth","kind":"TypeRef","source":{"column":2,"end_column":12,"end_line":21,"line":21,"path":"packages/autonomous-identity/core/src/interfaces/AIPersistenceCore.ts"},"symbol":"cp:TypeRef"},{"attrs":{"name":"getIdentity"},"id":"n:typeref:getIdentity","kind":"TypeRef","source":{"column":2,"end_column":14,"end_line":27,"line":27,"path":"packages/autonomous-identity/core/src/interfaces/AIPersistenceCore.ts"},"symbol":"cp:TypeRef"},{"attrs":{"name":"getStatus"},"id":"n:typeref:getStatus","kind":"TypeRef","source":{"column":2,"end_column":12,"end_line":20,"line":20,"path":"packages/autonomous-identity/core/src/interfaces/AIPersistenceCore.ts"},"symbol":"cp:TypeRef"},{"attrs":{"name":"initialize"},"id":"n:typeref:initialize","kind":"TypeRef","source":{"column":2,"end_column":13,"end_line":18,"line":18,"path":"packages/autonomous-identity/core/src/interfaces/AIPersistenceCore.ts"},"symbol":"cp:TypeRef"},{"attrs":{"name":"retrieveMemory"},"id":"n:typeref:retrieveMemory","kind":"TypeRef","source":{"column":2,"end_column":17,"end_line":31,"line":31,"path":"packages/autonomous-identity/core/src/interfaces/AIPersistenceCore.ts"},"symbol":"cp:TypeRef"},{"attrs":{"name":"shutdown"},"id":"n:typeref:shutdown","kind":"TypeRef","source":{"column":2,"end_column":11,"end_line":19,"line":19,"path":"packages/autonomous-identity/core/src/interfaces/AIPersistenceCore.ts"},"symbol":"cp:TypeRef"},{"attrs":{"name":"storeMemory"},"id":"n:typeref:storeMemory","kind":"TypeRef","source":{"column":2,"end_column":14,"end_line":30,"line":30,"path":"packages/autonomous-identity/core/src/interfaces/AIPersistenceCore.ts"},"symbol":"cp:TypeRef"},{"attrs":{"name":"updateIdentity"},"id":"n:typeref:updateIdentity","kind":"TypeRef","source":{"column":2,"end_column":17,"end_line":25,"line":25,"path":"packages/autonomous-identity/core/src/interfaces/AIPersistenceCore.ts"},"symbol":"cp:TypeRef"}],"provenance":{"parser":"typescript-regex","parser_version":"v0","source_path":"packages/autonomous-identity/core/src/interfaces/AIPersistenceCore.ts"},"v":"ak.asg.v0"}
